Workbook

Sheet Reporte Diario
D2: DATOS REPORTE ASISTENCIA DIARIO
D3: PROYECTO: | E3: EIMI00359 | G3: =CONCATENATE("PROYECTO:"," ",_xlfn.XLOOKUP(E3,'Data obras'!B:B,'Data obras'!C:C,"Seleccionar Proyecto")) -> PROYECTO: OO.CC y Montaje Electromecánico MAPA Calderas
D4: FECHA ASISTENCIA: | E4: 46152
D5: CORREO A ENVIAR | E5: atapiab@eimontajes.cl
D6: VERSIÓN | E6: 0
B8: N° | C8: ROL | D8: RUT | E8: NOMBRE | F8: CARGO | G8: FECHA DE INGRESO | H8: JORNADA | I8: TURNO | J8: LUGAR DE TRABAJO | K8: ASISTENCIA | L8: UNIDAD | M8: TIPO MO | N8: GENERO | O8: REGIÓN | P8: CIUDAD | Q8: COMUNA | R8: TELEFONO

Sheet Resumen
D2: DATOS REPORTE ASISTENCIA DIARIO
D3: PROYECTO: | E3: ='Reporte Diario'!E3 -> EIMI00359 | G3: =CONCATENATE("RESUMEN REPORTE DIARIO PROYECTO",": ",_xlfn.XLOOKUP('Reporte Diario'!E3,'Data obras'!B:B,'Data obras'!C:C,"Seleccionar Proyecto")) -> RESUMEN REPORTE DIARIO PROYECTO: OO.CC y Montaje Electromecánico MAPA Calderas
D4: FECHA ASISTENCIA: | E4: =+'Reporte Diario'!E4 -> 46152
D5: VERSIÓN | E5: ='Reporte Diario'!E6 -> 0
Q7: TURNOS EN OBRA | U7: TURNOS EN DESCANSO
B9: ASISTENCIA | C9: OBRA | D9: DESCANSO | E9: LICENCIA MEDICA | F9: PERMISO C/S | G9: PERMISO S/S | H9: FALLA | I9: VACACIONES | J9: TELETRABAJO | K9: OFICINA SANTIAGO | L9: EN TRANSITO | M9: ACREDITADO | N9: TOTAL GENERAL | P9: TURNOS | Q9: 05x02 | R9: 08x06 | S9: 14x14 | T9: 15x13 | U9: 05x02 | V9: 08x06 | W9: 14x14 | X9: 15x13 | Y9: OTROS | Z9: TOTAL GENERAL
B10: MOD | C10: =SUM(C11:C21) -> 0 | D10: =SUM(D11:D21) -> 0 | E10: =SUM(E11:E21) -> 0 | F10: =SUM(F11:F21) -> 0 | G10: =SUM(G11:G21) -> 0 | H10: =SUM(H11:H21) -> 0 | I10: =SUM(I11:I21) -> 0 | J10: =SUM(J11:J21) -> 0 | ... N10: =SUM(N11:N21) -> 0 | P10: MOD | Q10: =SUM(Q11:Q22) -> 0 | R10: =SUM(R11:R22) -> 0 | S10: =SUM(S11:S22) -> 0 | T10: =SUM(T11:T22) -> 0 | U10: =SUM(U11:U22) -> 0 | V10: =SUM(V11:V22) -> 0 | W10: =SUM(W11:W22) -> 0 | X10: =SUM(X11:X22) -> 0 | Y10: =SUM(Y11:Y22) -> 0 | Z10: =SUM(Q10:Y10) -> 0
B11: ANDAMIOS | C11: =COUNTIFS('Reporte Diario'!$K:$K,Resumen!C$9,'Reporte Diario'!$L:$L,Resumen!$B11,'Reporte Diario'!$M:$M,Resumen!$B$10) -> 0 | D11: =COUNTIFS('Reporte Diario'!$K:$K,Resumen!D$9,'Reporte Diario'!$L:$L,Resumen!$B11,'Reporte Diario'!$M:$M,Resumen!$B$10) -> 0 | E11: =COUNTIFS('Reporte Diario'!$K:$K,Resumen!E$9,'Reporte Diario'!$L:$L,Resumen!$B11,'Reporte Diario'!$M:$M,Resumen!$B$10) -> 0 | F11: =COUNTIFS('Reporte Diario'!$K:$K,Resumen!F$9,'Reporte Diario'!$L:$L,Resumen!$B11,'Reporte Diario'!$M:$M,Resumen!$B$10) -> 0 | G11: =COUNTIFS('Reporte Diario'!$K:$K,Resumen!G$9,'Reporte Diario'!$L:$L,Resumen!$B11,'Reporte Diario'!$M:$M,Resumen!$B$10) -> 0 | H11: =COUNTIFS('Reporte Diario'!$K:$K,Resumen!H$9,'Reporte Diario'!$L:$L,Resumen!$B11,'Reporte Diario'!$M:$M,Resumen!$B$10) -> 0 | I11: =COUNTIFS('Reporte Diario'!$K:$K,Resumen!I$9,'Reporte Diario'!$L:$L,Resumen!$B11,'Reporte Diario'!$M:$M,Resumen!$B$10) -> 0 | J11: =COUNTIFS('Reporte Diario'!$K:$K,Resumen!J$9,'Reporte Diario'!$L:$L,Resumen!$B11,'Reporte Diario'!$M:$M,Resumen!$B$10) -> 0 | ... M11: =COUNTIFS('Reporte Diario'!$K:$K,Resumen!M$9,'Reporte Diario'!$L:$L,Resumen!$B11,'Reporte Diario'!$M:$M,Resumen!$B$10) -> 0 | N11: =SUM(C11:M11) -> 0 | P11: ANDAMIOS | Q11: =COUNTIFS('Reporte Diario'!$H:$H,Resumen!Q$9,'Reporte Diario'!$L:$L,$P11,'Reporte Diario'!$M:$M,$P$10,'Reporte Diario'!$K:$K,"OBRA") -> 0 | R11: =COUNTIFS('Reporte Diario'!$H:$H,Resumen!R$9,'Reporte Diario'!$L:$L,$P11,'Reporte Diario'!$M:$M,$P$10,'Reporte Diario'!$K:$K,"OBRA") -> 0 | S11: =COUNTIFS('Reporte Diario'!$H:$H,Resumen!S$9,'Reporte Diario'!$L:$L,$P11,'Reporte Diario'!$M:$M,$P$10,'Reporte Diario'!$K:$K,"OBRA") -> 0 | T11: =COUNTIFS('Reporte Diario'!$H:$H,Resumen!T$9,'Reporte Diario'!$L:$L,$P11,'Reporte Diario'!$M:$M,$P$10,'Reporte Diario'!$K:$K,"OBRA") -> 0 | U11: =COUNTIFS('Reporte Diario'!$H:$H,Resumen!U$9,'Reporte Diario'!$L:$L,$P11,'Reporte Diario'!$M:$M,$P$10,'Reporte Diario'!$K:$K,"DESCANSO") -> 0 | V11: =COUNTIFS('Reporte Diario'!$H:$H,Resumen!V$9,'Reporte Diario'!$L:$L,$P11,'Reporte Diario'!$M:$M,$P$10,'Reporte Diario'!$K:$K,"DESCANSO") -> 0 | W11: =COUNTIFS('Reporte Diario'!$H:$H,Resumen!W$9,'Reporte Diario'!$L:$L,$P11,'Reporte Diario'!$M:$M,$P$10,'Reporte Diario'!$K:$K,"DESCANSO") -> 0 | X11: =COUNTIFS('Reporte Diario'!$H:$H,Resumen!X$9,'Reporte Diario'!$L:$L,$P11,'Reporte Diario'!$M:$M,$P$10,'Reporte Diario'!$K:$K,"DESCANSO") -> 0 | Y11: =SUM(E11:M11) -> 0 | Z11: =SUM(Q11:Y11) -> 0
B12: AISLACIÓN | C12: =COUNTIFS('Reporte Diario'!$K:$K,Resumen!C$9,'Reporte Diario'!$L:$L,Resumen!$B12,'Reporte Diario'!$M:$M,Resumen!$B$10) -> 0 | D12: =COUNTIFS('Reporte Diario'!$K:$K,Resumen!D$9,'Reporte Diario'!$L:$L,Resumen!$B12,'Reporte Diario'!$M:$M,Resumen!$B$10) -> 0 | E12: =COUNTIFS('Reporte Diario'!$K:$K,Resumen!E$9,'Reporte Diario'!$L:$L,Resumen!$B12,'Reporte Diario'!$M:$M,Resumen!$B$10) -> 0 | F12: =COUNTIFS('Reporte Diario'!$K:$K,Resumen!F$9,'Reporte Diario'!$L:$L,Resumen!$B12,'Reporte Diario'!$M:$M,Resumen!$B$10) -> 0 | G12: =COUNTIFS('Reporte Diario'!$K:$K,Resumen!G$9,'Reporte Diario'!$L:$L,Resumen!$B12,'Reporte Diario'!$M:$M,Resumen!$B$10) -> 0 | H12: =COUNTIFS('Reporte Diario'!$K:$K,Resumen!H$9,'Reporte Diario'!$L:$L,Resumen!$B12,'Reporte Diario'!$M:$M,Resumen!$B$10) -> 0 | I12: =COUNTIFS('Reporte Diario'!$K:$K,Resumen!I$9,'Reporte Diario'!$L:$L,Resumen!$B12,'Reporte Diario'!$M:$M,Resumen!$B$10) -> 0 | J12: =COUNTIFS('Reporte Diario'!$K:$K,Resumen!J$9,'Reporte Diario'!$L:$L,Resumen!$B12,'Reporte Diario'!$M:$M,Resumen!$B$10) -> 0 | ... M12: =COUNTIFS('Reporte Diario'!$K:$K,Resumen!M$9,'Reporte Diario'!$L:$L,Resumen!$B12,'Reporte Diario'!$M:$M,Resumen!$B$10) -> 0 | N12: =SUM(C12:M12) -> 0 | P12: AISLACIÓN | Q12: =COUNTIFS('Reporte Diario'!$H:$H,Resumen!Q$9,'Reporte Diario'!$L:$L,$P12,'Reporte Diario'!$M:$M,$P$10,'Reporte Diario'!$K:$K,"OBRA") -> 0 | R12: =COUNTIFS('Reporte Diario'!$H:$H,Resumen!R$9,'Reporte Diario'!$L:$L,$P12,'Reporte Diario'!$M:$M,$P$10,'Reporte Diario'!$K:$K,"OBRA") -> 0 | S12: =COUNTIFS('Reporte Diario'!$H:$H,Resumen!S$9,'Reporte Diario'!$L:$L,$P12,'Reporte Diario'!$M:$M,$P$10,'Reporte Diario'!$K:$K,"OBRA") -> 0 | T12: =COUNTIFS('Reporte Diario'!$H:$H,Resumen!T$9,'Reporte Diario'!$L:$L,$P12,'Reporte Diario'!$M:$M,$P$10,'Reporte Diario'!$K:$K,"OBRA") -> 0 | U12: =COUNTIFS('Reporte Diario'!$H:$H,Resumen!U$9,'Reporte Diario'!$L:$L,$P12,'Reporte Diario'!$M:$M,$P$10,'Reporte Diario'!$K:$K,"DESCANSO") -> 0 | V12: =COUNTIFS('Reporte Diario'!$H:$H,Resumen!V$9,'Reporte Diario'!$L:$L,$P12,'Reporte Diario'!$M:$M,$P$10,'Reporte Diario'!$K:$K,"DESCANSO") -> 0 | W12: =COUNTIFS('Reporte Diario'!$H:$H,Resumen!W$9,'Reporte Diario'!$L:$L,$P12,'Reporte Diario'!$M:$M,$P$10,'Reporte Diario'!$K:$K,"DESCANSO") -> 0 | X12: =COUNTIFS('Reporte Diario'!$H:$H,Resumen!X$9,'Reporte Diario'!$L:$L,$P12,'Reporte Diario'!$M:$M,$P$10,'Reporte Diario'!$K:$K,"DESCANSO") -> 0 | Y12: =SUM(E12:M12) -> 0 | Z12: =SUM(Q12:Y12) -> 0
B13: CAÑERIA | C13: =COUNTIFS('Reporte Diario'!$K:$K,Resumen!C$9,'Reporte Diario'!$L:$L,Resumen!$B13,'Reporte Diario'!$M:$M,Resumen!$B$10) -> 0 | D13: =COUNTIFS('Reporte Diario'!$K:$K,Resumen!D$9,'Reporte Diario'!$L:$L,Resumen!$B13,'Reporte Diario'!$M:$M,Resumen!$B$10) -> 0 | E13: =COUNTIFS('Reporte Diario'!$K:$K,Resumen!E$9,'Reporte Diario'!$L:$L,Resumen!$B13,'Reporte Diario'!$M:$M,Resumen!$B$10) -> 0 | F13: =COUNTIFS('Reporte Diario'!$K:$K,Resumen!F$9,'Reporte Diario'!$L:$L,Resumen!$B13,'Reporte Diario'!$M:$M,Resumen!$B$10) -> 0 | G13: =COUNTIFS('Reporte Diario'!$K:$K,Resumen!G$9,'Reporte Diario'!$L:$L,Resumen!$B13,'Reporte Diario'!$M:$M,Resumen!$B$10) -> 0 | H13: =COUNTIFS('Reporte Diario'!$K:$K,Resumen!H$9,'Reporte Diario'!$L:$L,Resumen!$B13,'Reporte Diario'!$M:$M,Resumen!$B$10) -> 0 | I13: =COUNTIFS('Reporte Diario'!$K:$K,Resumen!I$9,'Reporte Diario'!$L:$L,Resumen!$B13,'Reporte Diario'!$M:$M,Resumen!$B$10) -> 0 | J13: =COUNTIFS('Reporte Diario'!$K:$K,Resumen!J$9,'Reporte Diario'!$L:$L,Resumen!$B13,'Reporte Diario'!$M:$M,Resumen!$B$10) -> 0 | ... M13: =COUNTIFS('Reporte Diario'!$K:$K,Resumen!M$9,'Reporte Diario'!$L:$L,Resumen!$B13,'Reporte Diario'!$M:$M,Resumen!$B$10) -> 0 | N13: =SUM(C13:M13) -> 0 | P13: CAÑERIA | Q13: =COUNTIFS('Reporte Diario'!$H:$H,Resumen!Q$9,'Reporte Diario'!$L:$L,$P13,'Reporte Diario'!$M:$M,$P$10,'Reporte Diario'!$K:$K,"OBRA") -> 0 | R13: =COUNTIFS('Reporte Diario'!$H:$H,Resumen!R$9,'Reporte Diario'!$L:$L,$P13,'Reporte Diario'!$M:$M,$P$10,'Reporte Diario'!$K:$K,"OBRA") -> 0 | S13: =COUNTIFS('Reporte Diario'!$H:$H,Resumen!S$9,'Reporte Diario'!$L:$L,$P13,'Reporte Diario'!$M:$M,$P$10,'Reporte Diario'!$K:$K,"OBRA") -> 0 | T13: =COUNTIFS('Reporte Diario'!$H:$H,Resumen!T$9,'Reporte Diario'!$L:$L,$P13,'Reporte Diario'!$M:$M,$P$10,'Reporte Diario'!$K:$K,"OBRA") -> 0 | U13: =COUNTIFS('Reporte Diario'!$H:$H,Resumen!U$9,'Reporte Diario'!$L:$L,$P13,'Reporte Diario'!$M:$M,$P$10,'Reporte Diario'!$K:$K,"DESCANSO") -> 0 | V13: =COUNTIFS('Reporte Diario'!$H:$H,Resumen!V$9,'Reporte Diario'!$L:$L,$P13,'Reporte Diario'!$M:$M,$P$10,'Reporte Diario'!$K:$K,"DESCANSO") -> 0 | W13: =COUNTIFS('Reporte Diario'!$H:$H,Resumen!W$9,'Reporte Diario'!$L:$L,$P13,'Reporte Diario'!$M:$M,$P$10,'Reporte Diario'!$K:$K,"DESCANSO") -> 0 | X13: =COUNTIFS('Reporte Diario'!$H:$H,Resumen!X$9,'Reporte Diario'!$L:$L,$P13,'Reporte Diario'!$M:$M,$P$10,'Reporte Diario'!$K:$K,"DESCANSO") -> 0 | Y13: =SUM(E13:M13) -> 0 | Z13: =SUM(Q13:Y13) -> 0
B14: INSTRUMENTACION | C14: =COUNTIFS('Reporte Diario'!$K:$K,Resumen!C$9,'Reporte Diario'!$L:$L,Resumen!$B14,'Reporte Diario'!$M:$M,Resumen!$B$10) -> 0 | D14: =COUNTIFS('Reporte Diario'!$K:$K,Resumen!D$9,'Reporte Diario'!$L:$L,Resumen!$B14,'Reporte Diario'!$M:$M,Resumen!$B$10) -> 0 | E14: =COUNTIFS('Reporte Diario'!$K:$K,Resumen!E$9,'Reporte Diario'!$L:$L,Resumen!$B14,'Reporte Diario'!$M:$M,Resumen!$B$10) -> 0 | F14: =COUNTIFS('Reporte Diario'!$K:$K,Resumen!F$9,'Reporte Diario'!$L:$L,Resumen!$B14,'Reporte Diario'!$M:$M,Resumen!$B$10) -> 0 | G14: =COUNTIFS('Reporte Diario'!$K:$K,Resumen!G$9,'Reporte Diario'!$L:$L,Resumen!$B14,'Reporte Diario'!$M:$M,Resumen!$B$10) -> 0 | H14: =COUNTIFS('Reporte Diario'!$K:$K,Resumen!H$9,'Reporte Diario'!$L:$L,Resumen!$B14,'Reporte Diario'!$M:$M,Resumen!$B$10) -> 0 | I14: =COUNTIFS('Reporte Diario'!$K:$K,Resumen!I$9,'Reporte Diario'!$L:$L,Resumen!$B14,'Reporte Diario'!$M:$M,Resumen!$B$10) -> 0 | J14: =COUNTIFS('Reporte Diario'!$K:$K,Resumen!J$9,'Reporte Diario'!$L:$L,Resumen!$B14,'Reporte Diario'!$M:$M,Resumen!$B$10) -> 0 | ... M14: =COUNTIFS('Reporte Diario'!$K:$K,Resumen!M$9,'Reporte Diario'!$L:$L,Resumen!$B14,'Reporte Diario'!$M:$M,Resumen!$B$10) -> 0 | N14: =SUM(C14:M14) -> 0 | P14: INSTRUMENTACION | Q14: =COUNTIFS('Reporte Diario'!$H:$H,Resumen!Q$9,'Reporte Diario'!$L:$L,$P14,'Reporte Diario'!$M:$M,$P$10,'Reporte Diario'!$K:$K,"OBRA") -> 0 | R14: =COUNTIFS('Reporte Diario'!$H:$H,Resumen!R$9,'Reporte Diario'!$L:$L,$P14,'Reporte Diario'!$M:$M,$P$10,'Reporte Diario'!$K:$K,"OBRA") -> 0 | S14: =COUNTIFS('Reporte Diario'!$H:$H,Resumen!S$9,'Reporte Diario'!$L:$L,$P14,'Reporte Diario'!$M:$M,$P$10,'Reporte Diario'!$K:$K,"OBRA") -> 0 | T14: =COUNTIFS('Reporte Diario'!$H:$H,Resumen!T$9,'Reporte Diario'!$L:$L,$P14,'Reporte Diario'!$M:$M,$P$10,'Reporte Diario'!$K:$K,"OBRA") -> 0 | U14: =COUNTIFS('Reporte Diario'!$H:$H,Resumen!U$9,'Reporte Diario'!$L:$L,$P14,'Reporte Diario'!$M:$M,$P$10,'Reporte Diario'!$K:$K,"DESCANSO") -> 0 | V14: =COUNTIFS('Reporte Diario'!$H:$H,Resumen!V$9,'Reporte Diario'!$L:$L,$P14,'Reporte Diario'!$M:$M,$P$10,'Reporte Diario'!$K:$K,"DESCANSO") -> 0 | W14: =COUNTIFS('Reporte Diario'!$H:$H,Resumen!W$9,'Reporte Diario'!$L:$L,$P14,'Reporte Diario'!$M:$M,$P$10,'Reporte Diario'!$K:$K,"DESCANSO") -> 0 | X14: =COUNTIFS('Reporte Diario'!$H:$H,Resumen!X$9,'Reporte Diario'!$L:$L,$P14,'Reporte Diario'!$M:$M,$P$10,'Reporte Diario'!$K:$K,"DESCANSO") -> 0 | Y14: =SUM(E14:M14) -> 0 | Z14: =SUM(Q14:Y14) -> 0
B15: ELECTRICOS | C15: =COUNTIFS('Reporte Diario'!$K:$K,Resumen!C$9,'Reporte Diario'!$L:$L,Resumen!$B15,'Reporte Diario'!$M:$M,Resumen!$B$10) -> 0 | D15: =COUNTIFS('Reporte Diario'!$K:$K,Resumen!D$9,'Reporte Diario'!$L:$L,Resumen!$B15,'Reporte Diario'!$M:$M,Resumen!$B$10) -> 0 | E15: =COUNTIFS('Reporte Diario'!$K:$K,Resumen!E$9,'Reporte Diario'!$L:$L,Resumen!$B15,'Reporte Diario'!$M:$M,Resumen!$B$10) -> 0 | F15: =COUNTIFS('Reporte Diario'!$K:$K,Resumen!F$9,'Reporte Diario'!$L:$L,Resumen!$B15,'Reporte Diario'!$M:$M,Resumen!$B$10) -> 0 | G15: =COUNTIFS('Reporte Diario'!$K:$K,Resumen!G$9,'Reporte Diario'!$L:$L,Resumen!$B15,'Reporte Diario'!$M:$M,Resumen!$B$10) -> 0 | H15: =COUNTIFS('Reporte Diario'!$K:$K,Resumen!H$9,'Reporte Diario'!$L:$L,Resumen!$B15,'Reporte Diario'!$M:$M,Resumen!$B$10) -> 0 | I15: =COUNTIFS('Reporte Diario'!$K:$K,Resumen!I$9,'Reporte Diario'!$L:$L,Resumen!$B15,'Reporte Diario'!$M:$M,Resumen!$B$10) -> 0 | J15: =COUNTIFS('Reporte Diario'!$K:$K,Resumen!J$9,'Reporte Diario'!$L:$L,Resumen!$B15,'Reporte Diario'!$M:$M,Resumen!$B$10) -> 0 | ... M15: =COUNTIFS('Reporte Diario'!$K:$K,Resumen!M$9,'Reporte Diario'!$L:$L,Resumen!$B15,'Reporte Diario'!$M:$M,Resumen!$B$10) -> 0 | N15: =SUM(C15:M15) -> 0 | P15: ELECTRICOS | Q15: =COUNTIFS('Reporte Diario'!$H:$H,Resumen!Q$9,'Reporte Diario'!$L:$L,$P15,'Reporte Diario'!$M:$M,$P$10,'Reporte Diario'!$K:$K,"OBRA") -> 0 | R15: =COUNTIFS('Reporte Diario'!$H:$H,Resumen!R$9,'Reporte Diario'!$L:$L,$P15,'Reporte Diario'!$M:$M,$P$10,'Reporte Diario'!$K:$K,"OBRA") -> 0 | S15: =COUNTIFS('Reporte Diario'!$H:$H,Resumen!S$9,'Reporte Diario'!$L:$L,$P15,'Reporte Diario'!$M:$M,$P$10,'Reporte Diario'!$K:$K,"OBRA") -> 0 | T15: =COUNTIFS('Reporte Diario'!$H:$H,Resumen!T$9,'Reporte Diario'!$L:$L,$P15,'Reporte Diario'!$M:$M,$P$10,'Reporte Diario'!$K:$K,"OBRA") -> 0 | U15: =COUNTIFS('Reporte Diario'!$H:$H,Resumen!U$9,'Reporte Diario'!$L:$L,$P15,'Reporte Diario'!$M:$M,$P$10,'Reporte Diario'!$K:$K,"DESCANSO") -> 0 | V15: =COUNTIFS('Reporte Diario'!$H:$H,Resumen!V$9,'Reporte Diario'!$L:$L,$P15,'Reporte Diario'!$M:$M,$P$10,'Reporte Diario'!$K:$K,"DESCANSO") -> 0 | W15: =COUNTIFS('Reporte Diario'!$H:$H,Resumen!W$9,'Reporte Diario'!$L:$L,$P15,'Reporte Diario'!$M:$M,$P$10,'Reporte Diario'!$K:$K,"DESCANSO") -> 0 | X15: =COUNTIFS('Reporte Diario'!$H:$H,Resumen!X$9,'Reporte Diario'!$L:$L,$P15,'Reporte Diario'!$M:$M,$P$10,'Reporte Diario'!$K:$K,"DESCANSO") -> 0 | Y15: =SUM(E15:M15) -> 0 | Z15: =SUM(Q15:Y15) -> 0
B16: ENFIERRADURA | C16: =COUNTIFS('Reporte Diario'!$K:$K,Resumen!C$9,'Reporte Diario'!$L:$L,Resumen!$B16,'Reporte Diario'!$M:$M,Resumen!$B$10) -> 0 | D16: =COUNTIFS('Reporte Diario'!$K:$K,Resumen!D$9,'Reporte Diario'!$L:$L,Resumen!$B16,'Reporte Diario'!$M:$M,Resumen!$B$10) -> 0 | E16: =COUNTIFS('Reporte Diario'!$K:$K,Resumen!E$9,'Reporte Diario'!$L:$L,Resumen!$B16,'Reporte Diario'!$M:$M,Resumen!$B$10) -> 0 | F16: =COUNTIFS('Reporte Diario'!$K:$K,Resumen!F$9,'Reporte Diario'!$L:$L,Resumen!$B16,'Reporte Diario'!$M:$M,Resumen!$B$10) -> 0 | G16: =COUNTIFS('Reporte Diario'!$K:$K,Resumen!G$9,'Reporte Diario'!$L:$L,Resumen!$B16,'Reporte Diario'!$M:$M,Resumen!$B$10) -> 0 | H16: =COUNTIFS('Reporte Diario'!$K:$K,Resumen!H$9,'Reporte Diario'!$L:$L,Resumen!$B16,'Reporte Diario'!$M:$M,Resumen!$B$10) -> 0 | I16: =COUNTIFS('Reporte Diario'!$K:$K,Resumen!I$9,'Reporte Diario'!$L:$L,Resumen!$B16,'Reporte Diario'!$M:$M,Resumen!$B$10) -> 0 | J16: =COUNTIFS('Reporte Diario'!$K:$K,Resumen!J$9,'Reporte Diario'!$L:$L,Resumen!$B16,'Reporte Diario'!$M:$M,Resumen!$B$10) -> 0 | ... M16: =COUNTIFS('Reporte Diario'!$K:$K,Resumen!M$9,'Reporte Diario'!$L:$L,Resumen!$B16,'Reporte Diario'!$M:$M,Resumen!$B$10) -> 0 | N16: =SUM(C16:M16) -> 0 | P16: ENFIERRADURA | Q16: =COUNTIFS('Reporte Diario'!$H:$H,Resumen!Q$9,'Reporte Diario'!$L:$L,$P16,'Reporte Diario'!$M:$M,$P$10,'Reporte Diario'!$K:$K,"OBRA") -> 0 | R16: =COUNTIFS('Reporte Diario'!$H:$H,Resumen!R$9,'Reporte Diario'!$L:$L,$P16,'Reporte Diario'!$M:$M,$P$10,'Reporte Diario'!$K:$K,"OBRA") -> 0 | S16: =COUNTIFS('Reporte Diario'!$H:$H,Resumen!S$9,'Reporte Diario'!$L:$L,$P16,'Reporte Diario'!$M:$M,$P$10,'Reporte Diario'!$K:$K,"OBRA") -> 0 | T16: =COUNTIFS('Reporte Diario'!$H:$H,Resumen!T$9,'Reporte Diario'!$L:$L,$P16,'Reporte Diario'!$M:$M,$P$10,'Reporte Diario'!$K:$K,"OBRA") -> 0 | U16: =COUNTIFS('Reporte Diario'!$H:$H,Resumen!U$9,'Reporte Diario'!$L:$L,$P16,'Reporte Diario'!$M:$M,$P$10,'Reporte Diario'!$K:$K,"DESCANSO") -> 0 | V16: =COUNTIFS('Reporte Diario'!$H:$H,Resumen!V$9,'Reporte Diario'!$L:$L,$P16,'Reporte Diario'!$M:$M,$P$10,'Reporte Diario'!$K:$K,"DESCANSO") -> 0 | W16: =COUNTIFS('Reporte Diario'!$H:$H,Resumen!W$9,'Reporte Diario'!$L:$L,$P16,'Reporte Diario'!$M:$M,$P$10,'Reporte Diario'!$K:$K,"DESCANSO") -> 0 | X16: =COUNTIFS('Reporte Diario'!$H:$H,Resumen!X$9,'Reporte Diario'!$L:$L,$P16,'Reporte Diario'!$M:$M,$P$10,'Reporte Diario'!$K:$K,"DESCANSO") -> 0 | Y16: =SUM(E16:M16) -> 0 | Z16: =SUM(Q16:Y16) -> 0
B17: ESTRUCTURA | C17: =COUNTIFS('Reporte Diario'!$K:$K,Resumen!C$9,'Reporte Diario'!$L:$L,Resumen!$B17,'Reporte Diario'!$M:$M,Resumen!$B$10) -> 0 | D17: =COUNTIFS('Reporte Diario'!$K:$K,Resumen!D$9,'Reporte Diario'!$L:$L,Resumen!$B17,'Reporte Diario'!$M:$M,Resumen!$B$10) -> 0 | E17: =COUNTIFS('Reporte Diario'!$K:$K,Resumen!E$9,'Reporte Diario'!$L:$L,Resumen!$B17,'Reporte Diario'!$M:$M,Resumen!$B$10) -> 0 | F17: =COUNTIFS('Reporte Diario'!$K:$K,Resumen!F$9,'Reporte Diario'!$L:$L,Resumen!$B17,'Reporte Diario'!$M:$M,Resumen!$B$10) -> 0 | G17: =COUNTIFS('Reporte Diario'!$K:$K,Resumen!G$9,'Reporte Diario'!$L:$L,Resumen!$B17,'Reporte Diario'!$M:$M,Resumen!$B$10) -> 0 | H17: =COUNTIFS('Reporte Diario'!$K:$K,Resumen!H$9,'Reporte Diario'!$L:$L,Resumen!$B17,'Reporte Diario'!$M:$M,Resumen!$B$10) -> 0 | I17: =COUNTIFS('Reporte Diario'!$K:$K,Resumen!I$9,'Reporte Diario'!$L:$L,Resumen!$B17,'Reporte Diario'!$M:$M,Resumen!$B$10) -> 0 | J17: =COUNTIFS('Reporte Diario'!$K:$K,Resumen!J$9,'Reporte Diario'!$L:$L,Resumen!$B17,'Reporte Diario'!$M:$M,Resumen!$B$10) -> 0 | ... M17: =COUNTIFS('Reporte Diario'!$K:$K,Resumen!M$9,'Reporte Diario'!$L:$L,Resumen!$B17,'Reporte Diario'!$M:$M,Resumen!$B$10) -> 0 | N17: =SUM(C17:M17) -> 0 | P17: ESTRUCTURA | Q17: =COUNTIFS('Reporte Diario'!$H:$H,Resumen!Q$9,'Reporte Diario'!$L:$L,$P17,'Reporte Diario'!$M:$M,$P$10,'Reporte Diario'!$K:$K,"OBRA") -> 0 | R17: =COUNTIFS('Reporte Diario'!$H:$H,Resumen!R$9,'Reporte Diario'!$L:$L,$P17,'Reporte Diario'!$M:$M,$P$10,'Reporte Diario'!$K:$K,"OBRA") -> 0 | S17: =COUNTIFS('Reporte Diario'!$H:$H,Resumen!S$9,'Reporte Diario'!$L:$L,$P17,'Reporte Diario'!$M:$M,$P$10,'Reporte Diario'!$K:$K,"OBRA") -> 0 | T17: =COUNTIFS('Reporte Diario'!$H:$H,Resumen!T$9,'Reporte Diario'!$L:$L,$P17,'Reporte Diario'!$M:$M,$P$10,'Reporte Diario'!$K:$K,"OBRA") -> 0 | U17: =COUNTIFS('Reporte Diario'!$H:$H,Resumen!U$9,'Reporte Diario'!$L:$L,$P17,'Reporte Diario'!$M:$M,$P$10,'Reporte Diario'!$K:$K,"DESCANSO") -> 0 | V17: =COUNTIFS('Reporte Diario'!$H:$H,Resumen!V$9,'Reporte Diario'!$L:$L,$P17,'Reporte Diario'!$M:$M,$P$10,'Reporte Diario'!$K:$K,"DESCANSO") -> 0 | W17: =COUNTIFS('Reporte Diario'!$H:$H,Resumen!W$9,'Reporte Diario'!$L:$L,$P17,'Reporte Diario'!$M:$M,$P$10,'Reporte Diario'!$K:$K,"DESCANSO") -> 0 | X17: =COUNTIFS('Reporte Diario'!$H:$H,Resumen!X$9,'Reporte Diario'!$L:$L,$P17,'Reporte Diario'!$M:$M,$P$10,'Reporte Diario'!$K:$K,"DESCANSO") -> 0 | Y17: =SUM(E17:M17) -> 0 | Z17: =SUM(Q17:Y17) -> 0
B18: MECANICA | C18: =COUNTIFS('Reporte Diario'!$K:$K,Resumen!C$9,'Reporte Diario'!$L:$L,Resumen!$B18,'Reporte Diario'!$M:$M,Resumen!$B$10) -> 0 | D18: =COUNTIFS('Reporte Diario'!$K:$K,Resumen!D$9,'Reporte Diario'!$L:$L,Resumen!$B18,'Reporte Diario'!$M:$M,Resumen!$B$10) -> 0 | E18: =COUNTIFS('Reporte Diario'!$K:$K,Resumen!E$9,'Reporte Diario'!$L:$L,Resumen!$B18,'Reporte Diario'!$M:$M,Resumen!$B$10) -> 0 | F18: =COUNTIFS('Reporte Diario'!$K:$K,Resumen!F$9,'Reporte Diario'!$L:$L,Resumen!$B18,'Reporte Diario'!$M:$M,Resumen!$B$10) -> 0 | G18: =COUNTIFS('Reporte Diario'!$K:$K,Resumen!G$9,'Reporte Diario'!$L:$L,Resumen!$B18,'Reporte Diario'!$M:$M,Resumen!$B$10) -> 0 | H18: =COUNTIFS('Reporte Diario'!$K:$K,Resumen!H$9,'Reporte Diario'!$L:$L,Resumen!$B18,'Reporte Diario'!$M:$M,Resumen!$B$10) -> 0 | I18: =COUNTIFS('Reporte Diario'!$K:$K,Resumen!I$9,'Reporte Diario'!$L:$L,Resumen!$B18,'Reporte Diario'!$M:$M,Resumen!$B$10) -> 0 | J18: =COUNTIFS('Reporte Diario'!$K:$K,Resumen!J$9,'Reporte Diario'!$L:$L,Resumen!$B18,'Reporte Diario'!$M:$M,Resumen!$B$10) -> 0 | ... M18: =COUNTIFS('Reporte Diario'!$K:$K,Resumen!M$9,'Reporte Diario'!$L:$L,Resumen!$B18,'Reporte Diario'!$M:$M,Resumen!$B$10) -> 0 | N18: =SUM(C18:M18) -> 0 | P18: MECANICA | Q18: =COUNTIFS('Reporte Diario'!$H:$H,Resumen!Q$9,'Reporte Diario'!$L:$L,$P18,'Reporte Diario'!$M:$M,$P$10,'Reporte Diario'!$K:$K,"OBRA") -> 0 | R18: =COUNTIFS('Reporte Diario'!$H:$H,Resumen!R$9,'Reporte Diario'!$L:$L,$P18,'Reporte Diario'!$M:$M,$P$10,'Reporte Diario'!$K:$K,"OBRA") -> 0 | S18: =COUNTIFS('Reporte Diario'!$H:$H,Resumen!S$9,'Reporte Diario'!$L:$L,$P18,'Reporte Diario'!$M:$M,$P$10,'Reporte Diario'!$K:$K,"OBRA") -> 0 | T18: =COUNTIFS('Reporte Diario'!$H:$H,Resumen!T$9,'Reporte Diario'!$L:$L,$P18,'Reporte Diario'!$M:$M,$P$10,'Reporte Diario'!$K:$K,"OBRA") -> 0 | U18: =COUNTIFS('Reporte Diario'!$H:$H,Resumen!U$9,'Reporte Diario'!$L:$L,$P18,'Reporte Diario'!$M:$M,$P$10,'Reporte Diario'!$K:$K,"DESCANSO") -> 0 | V18: =COUNTIFS('Reporte Diario'!$H:$H,Resumen!V$9,'Reporte Diario'!$L:$L,$P18,'Reporte Diario'!$M:$M,$P$10,'Reporte Diario'!$K:$K,"DESCANSO") -> 0 | W18: =COUNTIFS('Reporte Diario'!$H:$H,Resumen!W$9,'Reporte Diario'!$L:$L,$P18,'Reporte Diario'!$M:$M,$P$10,'Reporte Diario'!$K:$K,"DESCANSO") -> 0 | X18: =COUNTIFS('Reporte Diario'!$H:$H,Resumen!X$9,'Reporte Diario'!$L:$L,$P18,'Reporte Diario'!$M:$M,$P$10,'Reporte Diario'!$K:$K,"DESCANSO") -> 0 | Y18: =SUM(E18:M18) -> 0 | Z18: =SUM(Q18:Y18) -> 0
B19: PINTURA | C19: =COUNTIFS('Reporte Diario'!$K:$K,Resumen!C$9,'Reporte Diario'!$L:$L,Resumen!$B19,'Reporte Diario'!$M:$M,Resumen!$B$10) -> 0 | D19: =COUNTIFS('Reporte Diario'!$K:$K,Resumen!D$9,'Reporte Diario'!$L:$L,Resumen!$B19,'Reporte Diario'!$M:$M,Resumen!$B$10) -> 0 | E19: =COUNTIFS('Reporte Diario'!$K:$K,Resumen!E$9,'Reporte Diario'!$L:$L,Resumen!$B19,'Reporte Diario'!$M:$M,Resumen!$B$10) -> 0 | F19: =COUNTIFS('Reporte Diario'!$K:$K,Resumen!F$9,'Reporte Diario'!$L:$L,Resumen!$B19,'Reporte Diario'!$M:$M,Resumen!$B$10) -> 0 | G19: =COUNTIFS('Reporte Diario'!$K:$K,Resumen!G$9,'Reporte Diario'!$L:$L,Resumen!$B19,'Reporte Diario'!$M:$M,Resumen!$B$10) -> 0 | H19: =COUNTIFS('Reporte Diario'!$K:$K,Resumen!H$9,'Reporte Diario'!$L:$L,Resumen!$B19,'Reporte Diario'!$M:$M,Resumen!$B$10) -> 0 | I19: =COUNTIFS('Reporte Diario'!$K:$K,Resumen!I$9,'Reporte Diario'!$L:$L,Resumen!$B19,'Reporte Diario'!$M:$M,Resumen!$B$10) -> 0 | J19: =COUNTIFS('Reporte Diario'!$K:$K,Resumen!J$9,'Reporte Diario'!$L:$L,Resumen!$B19,'Reporte Diario'!$M:$M,Resumen!$B$10) -> 0 | ... M19: =COUNTIFS('Reporte Diario'!$K:$K,Resumen!M$9,'Reporte Diario'!$L:$L,Resumen!$B19,'Reporte Diario'!$M:$M,Resumen!$B$10) -> 0 | N19: =SUM(C19:M19) -> 0 | P19: PINTURA | Q19: =COUNTIFS('Reporte Diario'!$H:$H,Resumen!Q$9,'Reporte Diario'!$L:$L,$P19,'Reporte Diario'!$M:$M,$P$10,'Reporte Diario'!$K:$K,"OBRA") -> 0 | R19: =COUNTIFS('Reporte Diario'!$H:$H,Resumen!R$9,'Reporte Diario'!$L:$L,$P19,'Reporte Diario'!$M:$M,$P$10,'Reporte Diario'!$K:$K,"OBRA") -> 0 | S19: =COUNTIFS('Reporte Diario'!$H:$H,Resumen!S$9,'Reporte Diario'!$L:$L,$P19,'Reporte Diario'!$M:$M,$P$10,'Reporte Diario'!$K:$K,"OBRA") -> 0 | T19: =COUNTIFS('Reporte Diario'!$H:$H,Resumen!T$9,'Reporte Diario'!$L:$L,$P19,'Reporte Diario'!$M:$M,$P$10,'Reporte Diario'!$K:$K,"OBRA") -> 0 | U19: =COUNTIFS('Reporte Diario'!$H:$H,Resumen!U$9,'Reporte Diario'!$L:$L,$P19,'Reporte Diario'!$M:$M,$P$10,'Reporte Diario'!$K:$K,"DESCANSO") -> 0 | V19: =COUNTIFS('Reporte Diario'!$H:$H,Resumen!V$9,'Reporte Diario'!$L:$L,$P19,'Reporte Diario'!$M:$M,$P$10,'Reporte Diario'!$K:$K,"DESCANSO") -> 0 | W19: =COUNTIFS('Reporte Diario'!$H:$H,Resumen!W$9,'Reporte Diario'!$L:$L,$P19,'Reporte Diario'!$M:$M,$P$10,'Reporte Diario'!$K:$K,"DESCANSO") -> 0 | X19: =COUNTIFS('Reporte Diario'!$H:$H,Resumen!X$9,'Reporte Diario'!$L:$L,$P19,'Reporte Diario'!$M:$M,$P$10,'Reporte Diario'!$K:$K,"DESCANSO") -> 0 | Y19: =SUM(E19:M19) -> 0 | Z19: =SUM(Q19:Y19) -> 0
B20: OBRAS CIVILES | C20: =COUNTIFS('Reporte Diario'!$K:$K,Resumen!C$9,'Reporte Diario'!$L:$L,Resumen!$B20,'Reporte Diario'!$M:$M,Resumen!$B$10) -> 0 | D20: =COUNTIFS('Reporte Diario'!$K:$K,Resumen!D$9,'Reporte Diario'!$L:$L,Resumen!$B20,'Reporte Diario'!$M:$M,Resumen!$B$10) -> 0 | E20: =COUNTIFS('Reporte Diario'!$K:$K,Resumen!E$9,'Reporte Diario'!$L:$L,Resumen!$B20,'Reporte Diario'!$M:$M,Resumen!$B$10) -> 0 | F20: =COUNTIFS('Reporte Diario'!$K:$K,Resumen!F$9,'Reporte Diario'!$L:$L,Resumen!$B20,'Reporte Diario'!$M:$M,Resumen!$B$10) -> 0 | G20: =COUNTIFS('Reporte Diario'!$K:$K,Resumen!G$9,'Reporte Diario'!$L:$L,Resumen!$B20,'Reporte Diario'!$M:$M,Resumen!$B$10) -> 0 | H20: =COUNTIFS('Reporte Diario'!$K:$K,Resumen!H$9,'Reporte Diario'!$L:$L,Resumen!$B20,'Reporte Diario'!$M:$M,Resumen!$B$10) -> 0 | I20: =COUNTIFS('Reporte Diario'!$K:$K,Resumen!I$9,'Reporte Diario'!$L:$L,Resumen!$B20,'Reporte Diario'!$M:$M,Resumen!$B$10) -> 0 | J20: =COUNTIFS('Reporte Diario'!$K:$K,Resumen!J$9,'Reporte Diario'!$L:$L,Resumen!$B20,'Reporte Diario'!$M:$M,Resumen!$B$10) -> 0 | ... M20: =COUNTIFS('Reporte Diario'!$K:$K,Resumen!M$9,'Reporte Diario'!$L:$L,Resumen!$B20,'Reporte Diario'!$M:$M,Resumen!$B$10) -> 0 | N20: =SUM(C20:M20) -> 0 | P20: OBRAS CIVILES | Q20: =COUNTIFS('Reporte Diario'!$H:$H,Resumen!Q$9,'Reporte Diario'!$L:$L,$P20,'Reporte Diario'!$M:$M,$P$10,'Reporte Diario'!$K:$K,"OBRA") -> 0 | R20: =COUNTIFS('Reporte Diario'!$H:$H,Resumen!R$9,'Reporte Diario'!$L:$L,$P20,'Reporte Diario'!$M:$M,$P$10,'Reporte Diario'!$K:$K,"OBRA") -> 0 | S20: =COUNTIFS('Reporte Diario'!$H:$H,Resumen!S$9,'Reporte Diario'!$L:$L,$P20,'Reporte Diario'!$M:$M,$P$10,'Reporte Diario'!$K:$K,"OBRA") -> 0 | T20: =COUNTIFS('Reporte Diario'!$H:$H,Resumen!T$9,'Reporte Diario'!$L:$L,$P20,'Reporte Diario'!$M:$M,$P$10,'Reporte Diario'!$K:$K,"OBRA") -> 0 | U20: =COUNTIFS('Reporte Diario'!$H:$H,Resumen!U$9,'Reporte Diario'!$L:$L,$P20,'Reporte Diario'!$M:$M,$P$10,'Reporte Diario'!$K:$K,"DESCANSO") -> 0 | V20: =COUNTIFS('Reporte Diario'!$H:$H,Resumen!V$9,'Reporte Diario'!$L:$L,$P20,'Reporte Diario'!$M:$M,$P$10,'Reporte Diario'!$K:$K,"DESCANSO") -> 0 | W20: =COUNTIFS('Reporte Diario'!$H:$H,Resumen!W$9,'Reporte Diario'!$L:$L,$P20,'Reporte Diario'!$M:$M,$P$10,'Reporte Diario'!$K:$K,"DESCANSO") -> 0 | X20: =COUNTIFS('Reporte Diario'!$H:$H,Resumen!X$9,'Reporte Diario'!$L:$L,$P20,'Reporte Diario'!$M:$M,$P$10,'Reporte Diario'!$K:$K,"DESCANSO") -> 0 | Y20: =SUM(E20:M20) -> 0 | Z20: =SUM(Q20:Y20) -> 0
B21: SOLDADURA | C21: =COUNTIFS('Reporte Diario'!$K:$K,Resumen!C$9,'Reporte Diario'!$L:$L,Resumen!$B21,'Reporte Diario'!$M:$M,Resumen!$B$10) -> 0 | D21: =COUNTIFS('Reporte Diario'!$K:$K,Resumen!D$9,'Reporte Diario'!$L:$L,Resumen!$B21,'Reporte Diario'!$M:$M,Resumen!$B$10) -> 0 | E21: =COUNTIFS('Reporte Diario'!$K:$K,Resumen!E$9,'Reporte Diario'!$L:$L,Resumen!$B21,'Reporte Diario'!$M:$M,Resumen!$B$10) -> 0 | F21: =COUNTIFS('Reporte Diario'!$K:$K,Resumen!F$9,'Reporte Diario'!$L:$L,Resumen!$B21,'Reporte Diario'!$M:$M,Resumen!$B$10) -> 0 | G21: =COUNTIFS('Reporte Diario'!$K:$K,Resumen!G$9,'Reporte Diario'!$L:$L,Resumen!$B21,'Reporte Diario'!$M:$M,Resumen!$B$10) -> 0 | H21: =COUNTIFS('Reporte Diario'!$K:$K,Resumen!H$9,'Reporte Diario'!$L:$L,Resumen!$B21,'Reporte Diario'!$M:$M,Resumen!$B$10) -> 0 | I21: =COUNTIFS('Reporte Diario'!$K:$K,Resumen!I$9,'Reporte Diario'!$L:$L,Resumen!$B21,'Reporte Diario'!$M:$M,Resumen!$B$10) -> 0 | J21: =COUNTIFS('Reporte Diario'!$K:$K,Resumen!J$9,'Reporte Diario'!$L:$L,Resumen!$B21,'Reporte Diario'!$M:$M,Resumen!$B$10) -> 0 | ... M21: =COUNTIFS('Reporte Diario'!$K:$K,Resumen!M$9,'Reporte Diario'!$L:$L,Resumen!$B21,'Reporte Diario'!$M:$M,Resumen!$B$10) -> 0 | N21: =SUM(C21:M21) -> 0 | P21: SOLDADURA | Q21: =COUNTIFS('Reporte Diario'!$H:$H,Resumen!Q$9,'Reporte Diario'!$L:$L,$P21,'Reporte Diario'!$M:$M,$P$10,'Reporte Diario'!$K:$K,"OBRA") -> 0 | R21: =COUNTIFS('Reporte Diario'!$H:$H,Resumen!R$9,'Reporte Diario'!$L:$L,$P21,'Reporte Diario'!$M:$M,$P$10,'Reporte Diario'!$K:$K,"OBRA") -> 0 | S21: =COUNTIFS('Reporte Diario'!$H:$H,Resumen!S$9,'Reporte Diario'!$L:$L,$P21,'Reporte Diario'!$M:$M,$P$10,'Reporte Diario'!$K:$K,"OBRA") -> 0 | T21: =COUNTIFS('Reporte Diario'!$H:$H,Resumen!T$9,'Reporte Diario'!$L:$L,$P21,'Reporte Diario'!$M:$M,$P$10,'Reporte Diario'!$K:$K,"OBRA") -> 0 | U21: =COUNTIFS('Reporte Diario'!$H:$H,Resumen!U$9,'Reporte Diario'!$L:$L,$P21,'Reporte Diario'!$M:$M,$P$10,'Reporte Diario'!$K:$K,"DESCANSO") -> 0 | V21: =COUNTIFS('Reporte Diario'!$H:$H,Resumen!V$9,'Reporte Diario'!$L:$L,$P21,'Reporte Diario'!$M:$M,$P$10,'Reporte Diario'!$K:$K,"DESCANSO") -> 0 | W21: =COUNTIFS('Reporte Diario'!$H:$H,Resumen!W$9,'Reporte Diario'!$L:$L,$P21,'Reporte Diario'!$M:$M,$P$10,'Reporte Diario'!$K:$K,"DESCANSO") -> 0 | X21: =COUNTIFS('Reporte Diario'!$H:$H,Resumen!X$9,'Reporte Diario'!$L:$L,$P21,'Reporte Diario'!$M:$M,$P$10,'Reporte Diario'!$K:$K,"DESCANSO") -> 0 | Y21: =SUM(E21:M21) -> 0 | Z21: =SUM(Q21:Y21) -> 0
B23: ASISTENCIA | C23: OBRA | D23: DESCANSO | E23: LICENCIA MEDICA | F23: PERMISO C/GOCE | G23: PERMISO S/GOCE | H23: FALLA | I23: VACACIONES | J23: TELETRABAJO | K23: OFICINA SANTIAGO | L23: EN TRANSITO | M23: ACREDITADO | N23: TOTAL GENERAL | P23: TURNOS | Q23: 05x02 | R23: 08x06 | S23: 14x14 | T23: 15x13 | U23: 05x02 | V23: 08x06 | W23: 14x14 | X23: 15x13 | Y23: OTROS | Z23: TOTAL GENERAL
B24: MOI | C24: =SUM(C25:C39) -> 0 | D24: =SUM(D25:D39) -> 0 | E24: =SUM(E25:E39) -> 0 | F24: =SUM(F25:F39) -> 0 | G24: =SUM(G25:G39) -> 0 | H24: =SUM(H25:H39) -> 0 | I24: =SUM(I25:I39) -> 0 | J24: =SUM(J25:J39) -> 0 | ... M24: =SUM(M25:M39) -> 0 | N24: =SUM(C24:L24) -> 0 | P24: MOI | Q24: =SUM(Q25:Q39) -> 0 | R24: =SUM(R25:R39) -> 0 | S24: =SUM(S25:S39) -> 0 | T24: =SUM(T25:T39) -> 0 | U24: =SUM(U25:U39) -> 0 | V24: =SUM(V25:V39) -> 0 | W24: =SUM(W25:W39) -> 0 | X24: =SUM(X25:X39) -> 0 | Y24: =SUM(Y25:Y39) -> 0 | Z24: =SUM(Q24:Y24) -> 0
B25: ADMINISTRACION | C25: =COUNTIFS('Reporte Diario'!$K:$K,Resumen!C$9,'Reporte Diario'!$L:$L,Resumen!$B25,'Reporte Diario'!$M:$M,$B$24) -> 0 | D25: =COUNTIFS('Reporte Diario'!$K:$K,Resumen!D$9,'Reporte Diario'!$L:$L,Resumen!$B25,'Reporte Diario'!$M:$M,$B$24) -> 0 | E25: =COUNTIFS('Reporte Diario'!$K:$K,Resumen!E$9,'Reporte Diario'!$L:$L,Resumen!$B25,'Reporte Diario'!$M:$M,$B$24) -> 0 | F25: =COUNTIFS('Reporte Diario'!$K:$K,Resumen!F$9,'Reporte Diario'!$L:$L,Resumen!$B25,'Reporte Diario'!$M:$M,$B$24) -> 0 | G25: =COUNTIFS('Reporte Diario'!$K:$K,Resumen!G$9,'Reporte Diario'!$L:$L,Resumen!$B25,'Reporte Diario'!$M:$M,$B$24) -> 0 | H25: =COUNTIFS('Reporte Diario'!$K:$K,Resumen!H$9,'Reporte Diario'!$L:$L,Resumen!$B25,'Reporte Diario'!$M:$M,$B$24) -> 0 | I25: =COUNTIFS('Reporte Diario'!$K:$K,Resumen!I$9,'Reporte Diario'!$L:$L,Resumen!$B25,'Reporte Diario'!$M:$M,$B$24) -> 0 | J25: =COUNTIFS('Reporte Diario'!$K:$K,Resumen!J$9,'Reporte Diario'!$L:$L,Resumen!$B25,'Reporte Diario'!$M:$M,$B$24) -> 0 | ... M25: =COUNTIFS('Reporte Diario'!$K:$K,Resumen!M$9,'Reporte Diario'!$L:$L,Resumen!$B25,'Reporte Diario'!$M:$M,$B$24) -> 0 | N25: =SUM(C25:L25) -> 0 | P25: ADMINISTRACION | Q25: =COUNTIFS('Reporte Diario'!$H:$H,Resumen!Q$23,'Reporte Diario'!$L:$L,$P25,'Reporte Diario'!$M:$M,$P$24,'Reporte Diario'!$K:$K,"OBRA") -> 0 | R25: =COUNTIFS('Reporte Diario'!$H:$H,Resumen!R$23,'Reporte Diario'!$L:$L,$P25,'Reporte Diario'!$M:$M,$P$24,'Reporte Diario'!$K:$K,"OBRA") -> 0 | S25: =COUNTIFS('Reporte Diario'!$H:$H,Resumen!S$23,'Reporte Diario'!$L:$L,$P25,'Reporte Diario'!$M:$M,$P$24,'Reporte Diario'!$K:$K,"OBRA") -> 0 | T25: =COUNTIFS('Reporte Diario'!$H:$H,Resumen!T$23,'Reporte Diario'!$L:$L,$P25,'Reporte Diario'!$M:$M,$P$24,'Reporte Diario'!$K:$K,"OBRA") -> 0 | U25: =COUNTIFS('Reporte Diario'!$H:$H,Resumen!U$23,'Reporte Diario'!$L:$L,$P25,'Reporte Diario'!$M:$M,$P$24,'Reporte Diario'!$K:$K,"DESCANSO") -> 0 | V25: =COUNTIFS('Reporte Diario'!$H:$H,Resumen!V$23,'Reporte Diario'!$L:$L,$P25,'Reporte Diario'!$M:$M,$P$24,'Reporte Diario'!$K:$K,"DESCANSO") -> 0 | W25: =COUNTIFS('Reporte Diario'!$H:$H,Resumen!W$23,'Reporte Diario'!$L:$L,$P25,'Reporte Diario'!$M:$M,$P$24,'Reporte Diario'!$K:$K,"DESCANSO") -> 0 | X25: =COUNTIFS('Reporte Diario'!$H:$H,Resumen!X$23,'Reporte Diario'!$L:$L,$P25,'Reporte Diario'!$M:$M,$P$24,'Reporte Diario'!$K:$K,"DESCANSO") -> 0 | Y25: =SUM(E25:M25) -> 0 | Z25: =SUM(Q25:Y25) -> 0
B26: BODEGA | C26: =COUNTIFS('Reporte Diario'!$K:$K,Resumen!C$9,'Reporte Diario'!$L:$L,Resumen!$B26,'Reporte Diario'!$M:$M,$B$24) -> 0 | D26: =COUNTIFS('Reporte Diario'!$K:$K,Resumen!D$9,'Reporte Diario'!$L:$L,Resumen!$B26,'Reporte Diario'!$M:$M,$B$24) -> 0 | E26: =COUNTIFS('Reporte Diario'!$K:$K,Resumen!E$9,'Reporte Diario'!$L:$L,Resumen!$B26,'Reporte Diario'!$M:$M,$B$24) -> 0 | F26: =COUNTIFS('Reporte Diario'!$K:$K,Resumen!F$9,'Reporte Diario'!$L:$L,Resumen!$B26,'Reporte Diario'!$M:$M,$B$24) -> 0 | G26: =COUNTIFS('Reporte Diario'!$K:$K,Resumen!G$9,'Reporte Diario'!$L:$L,Resumen!$B26,'Reporte Diario'!$M:$M,$B$24) -> 0 | H26: =COUNTIFS('Reporte Diario'!$K:$K,Resumen!H$9,'Reporte Diario'!$L:$L,Resumen!$B26,'Reporte Diario'!$M:$M,$B$24) -> 0 | I26: =COUNTIFS('Reporte Diario'!$K:$K,Resumen!I$9,'Reporte Diario'!$L:$L,Resumen!$B26,'Reporte Diario'!$M:$M,$B$24) -> 0 | J26: =COUNTIFS('Reporte Diario'!$K:$K,Resumen!J$9,'Reporte Diario'!$L:$L,Resumen!$B26,'Reporte Diario'!$M:$M,$B$24) -> 0 | ... M26: =COUNTIFS('Reporte Diario'!$K:$K,Resumen!M$9,'Reporte Diario'!$L:$L,Resumen!$B26,'Reporte Diario'!$M:$M,$B$24) -> 0 | N26: =SUM(C26:L26) -> 0 | P26: BODEGA | Q26: =COUNTIFS('Reporte Diario'!$H:$H,Resumen!Q$23,'Reporte Diario'!$L:$L,$P26,'Reporte Diario'!$M:$M,$P$24,'Reporte Diario'!$K:$K,"OBRA") -> 0 | R26: =COUNTIFS('Reporte Diario'!$H:$H,Resumen!R$23,'Reporte Diario'!$L:$L,$P26,'Reporte Diario'!$M:$M,$P$24,'Reporte Diario'!$K:$K,"OBRA") -> 0 | S26: =COUNTIFS('Reporte Diario'!$H:$H,Resumen!S$23,'Reporte Diario'!$L:$L,$P26,'Reporte Diario'!$M:$M,$P$24,'Reporte Diario'!$K:$K,"OBRA") -> 0 | T26: =COUNTIFS('Reporte Diario'!$H:$H,Resumen!T$23,'Reporte Diario'!$L:$L,$P26,'Reporte Diario'!$M:$M,$P$24,'Reporte Diario'!$K:$K,"OBRA") -> 0 | U26: =COUNTIFS('Reporte Diario'!$H:$H,Resumen!U$23,'Reporte Diario'!$L:$L,$P26,'Reporte Diario'!$M:$M,$P$24,'Reporte Diario'!$K:$K,"DESCANSO") -> 0 | V26: =COUNTIFS('Reporte Diario'!$H:$H,Resumen!V$23,'Reporte Diario'!$L:$L,$P26,'Reporte Diario'!$M:$M,$P$24,'Reporte Diario'!$K:$K,"DESCANSO") -> 0 | W26: =COUNTIFS('Reporte Diario'!$H:$H,Resumen!W$23,'Reporte Diario'!$L:$L,$P26,'Reporte Diario'!$M:$M,$P$24,'Reporte Diario'!$K:$K,"DESCANSO") -> 0 | X26: =COUNTIFS('Reporte Diario'!$H:$H,Resumen!X$23,'Reporte Diario'!$L:$L,$P26,'Reporte Diario'!$M:$M,$P$24,'Reporte Diario'!$K:$K,"DESCANSO") -> 0 | Y26: =SUM(E26:M26) -> 0 | Z26: =SUM(Q26:Y26) -> 0
B27: ELECTRICOS MANTENCION | C27: =COUNTIFS('Reporte Diario'!$K:$K,Resumen!C$9,'Reporte Diario'!$L:$L,Resumen!$B27,'Reporte Diario'!$M:$M,$B$24) -> 0 | D27: =COUNTIFS('Reporte Diario'!$K:$K,Resumen!D$9,'Reporte Diario'!$L:$L,Resumen!$B27,'Reporte Diario'!$M:$M,$B$24) -> 0 | E27: =COUNTIFS('Reporte Diario'!$K:$K,Resumen!E$9,'Reporte Diario'!$L:$L,Resumen!$B27,'Reporte Diario'!$M:$M,$B$24) -> 0 | F27: =COUNTIFS('Reporte Diario'!$K:$K,Resumen!F$9,'Reporte Diario'!$L:$L,Resumen!$B27,'Reporte Diario'!$M:$M,$B$24) -> 0 | G27: =COUNTIFS('Reporte Diario'!$K:$K,Resumen!G$9,'Reporte Diario'!$L:$L,Resumen!$B27,'Reporte Diario'!$M:$M,$B$24) -> 0 | H27: =COUNTIFS('Reporte Diario'!$K:$K,Resumen!H$9,'Reporte Diario'!$L:$L,Resumen!$B27,'Reporte Diario'!$M:$M,$B$24) -> 0 | I27: =COUNTIFS('Reporte Diario'!$K:$K,Resumen!I$9,'Reporte Diario'!$L:$L,Resumen!$B27,'Reporte Diario'!$M:$M,$B$24) -> 0 | J27: =COUNTIFS('Reporte Diario'!$K:$K,Resumen!J$9,'Reporte Diario'!$L:$L,Resumen!$B27,'Reporte Diario'!$M:$M,$B$24) -> 0 | ... M27: =COUNTIFS('Reporte Diario'!$K:$K,Resumen!M$9,'Reporte Diario'!$L:$L,Resumen!$B27,'Reporte Diario'!$M:$M,$B$24) -> 0 | N27: =SUM(C27:L27) -> 0 | P27: ELECTRICOS MANTENCION | Q27: =COUNTIFS('Reporte Diario'!$H:$H,Resumen!Q$23,'Reporte Diario'!$L:$L,$P27,'Reporte Diario'!$M:$M,$P$24,'Reporte Diario'!$K:$K,"OBRA") -> 0 | R27: =COUNTIFS('Reporte Diario'!$H:$H,Resumen!R$23,'Reporte Diario'!$L:$L,$P27,'Reporte Diario'!$M:$M,$P$24,'Reporte Diario'!$K:$K,"OBRA") -> 0 | S27: =COUNTIFS('Reporte Diario'!$H:$H,Resumen!S$23,'Reporte Diario'!$L:$L,$P27,'Reporte Diario'!$M:$M,$P$24,'Reporte Diario'!$K:$K,"OBRA") -> 0 | T27: =COUNTIFS('Reporte Diario'!$H:$H,Resumen!T$23,'Reporte Diario'!$L:$L,$P27,'Reporte Diario'!$M:$M,$P$24,'Reporte Diario'!$K:$K,"OBRA") -> 0 | U27: =COUNTIFS('Reporte Diario'!$H:$H,Resumen!U$23,'Reporte Diario'!$L:$L,$P27,'Reporte Diario'!$M:$M,$P$24,'Reporte Diario'!$K:$K,"DESCANSO") -> 0 | V27: =COUNTIFS('Reporte Diario'!$H:$H,Resumen!V$23,'Reporte Diario'!$L:$L,$P27,'Reporte Diario'!$M:$M,$P$24,'Reporte Diario'!$K:$K,"DESCANSO") -> 0 | W27: =COUNTIFS('Reporte Diario'!$H:$H,Resumen!W$23,'Reporte Diario'!$L:$L,$P27,'Reporte Diario'!$M:$M,$P$24,'Reporte Diario'!$K:$K,"DESCANSO") -> 0 | X27: =COUNTIFS('Reporte Diario'!$H:$H,Resumen!X$23,'Reporte Diario'!$L:$L,$P27,'Reporte Diario'!$M:$M,$P$24,'Reporte Diario'!$K:$K,"DESCANSO") -> 0 | Y27: =SUM(E27:M27) -> 0 | Z27: =SUM(Q27:Y27) -> 0
B28: EQUIPOS | C28: =COUNTIFS('Reporte Diario'!$K:$K,Resumen!C$9,'Reporte Diario'!$L:$L,Resumen!$B28,'Reporte Diario'!$M:$M,$B$24) -> 0 | D28: =COUNTIFS('Reporte Diario'!$K:$K,Resumen!D$9,'Reporte Diario'!$L:$L,Resumen!$B28,'Reporte Diario'!$M:$M,$B$24) -> 0 | E28: =COUNTIFS('Reporte Diario'!$K:$K,Resumen!E$9,'Reporte Diario'!$L:$L,Resumen!$B28,'Reporte Diario'!$M:$M,$B$24) -> 0 | F28: =COUNTIFS('Reporte Diario'!$K:$K,Resumen!F$9,'Reporte Diario'!$L:$L,Resumen!$B28,'Reporte Diario'!$M:$M,$B$24) -> 0 | G28: =COUNTIFS('Reporte Diario'!$K:$K,Resumen!G$9,'Reporte Diario'!$L:$L,Resumen!$B28,'Reporte Diario'!$M:$M,$B$24) -> 0 | H28: =COUNTIFS('Reporte Diario'!$K:$K,Resumen!H$9,'Reporte Diario'!$L:$L,Resumen!$B28,'Reporte Diario'!$M:$M,$B$24) -> 0 | I28: =COUNTIFS('Reporte Diario'!$K:$K,Resumen!I$9,'Reporte Diario'!$L:$L,Resumen!$B28,'Reporte Diario'!$M:$M,$B$24) -> 0 | J28: =COUNTIFS('Reporte Diario'!$K:$K,Resumen!J$9,'Reporte Diario'!$L:$L,Resumen!$B28,'Reporte Diario'!$M:$M,$B$24) -> 0 | ... M28: =COUNTIFS('Reporte Diario'!$K:$K,Resumen!M$9,'Reporte Diario'!$L:$L,Resumen!$B28,'Reporte Diario'!$M:$M,$B$24) -> 0 | N28: =SUM(C28:L28) -> 0 | P28: EQUIPOS | Q28: =COUNTIFS('Reporte Diario'!$H:$H,Resumen!Q$23,'Reporte Diario'!$L:$L,$P28,'Reporte Diario'!$M:$M,$P$24,'Reporte Diario'!$K:$K,"OBRA") -> 0 | R28: =COUNTIFS('Reporte Diario'!$H:$H,Resumen!R$23,'Reporte Diario'!$L:$L,$P28,'Reporte Diario'!$M:$M,$P$24,'Reporte Diario'!$K:$K,"OBRA") -> 0 | S28: =COUNTIFS('Reporte Diario'!$H:$H,Resumen!S$23,'Reporte Diario'!$L:$L,$P28,'Reporte Diario'!$M:$M,$P$24,'Reporte Diario'!$K:$K,"OBRA") -> 0 | T28: =COUNTIFS('Reporte Diario'!$H:$H,Resumen!T$23,'Reporte Diario'!$L:$L,$P28,'Reporte Diario'!$M:$M,$P$24,'Reporte Diario'!$K:$K,"OBRA") -> 0 | U28: =COUNTIFS('Reporte Diario'!$H:$H,Resumen!U$23,'Reporte Diario'!$L:$L,$P28,'Reporte Diario'!$M:$M,$P$24,'Reporte Diario'!$K:$K,"DESCANSO") -> 0 | V28: =COUNTIFS('Reporte Diario'!$H:$H,Resumen!V$23,'Reporte Diario'!$L:$L,$P28,'Reporte Diario'!$M:$M,$P$24,'Reporte Diario'!$K:$K,"DESCANSO") -> 0 | W28: =COUNTIFS('Reporte Diario'!$H:$H,Resumen!W$23,'Reporte Diario'!$L:$L,$P28,'Reporte Diario'!$M:$M,$P$24,'Reporte Diario'!$K:$K,"DESCANSO") -> 0 | X28: =COUNTIFS('Reporte Diario'!$H:$H,Resumen!X$23,'Reporte Diario'!$L:$L,$P28,'Reporte Diario'!$M:$M,$P$24,'Reporte Diario'!$K:$K,"DESCANSO") -> 0 | Y28: =SUM(E28:M28) -> 0 | Z28: =SUM(Q28:Y28) -> 0
B29: INGENIERIA | C29: =COUNTIFS('Reporte Diario'!$K:$K,Resumen!C$9,'Reporte Diario'!$L:$L,Resumen!$B29,'Reporte Diario'!$M:$M,$B$24) -> 0 | D29: =COUNTIFS('Reporte Diario'!$K:$K,Resumen!D$9,'Reporte Diario'!$L:$L,Resumen!$B29,'Reporte Diario'!$M:$M,$B$24) -> 0 | E29: =COUNTIFS('Reporte Diario'!$K:$K,Resumen!E$9,'Reporte Diario'!$L:$L,Resumen!$B29,'Reporte Diario'!$M:$M,$B$24) -> 0 | F29: =COUNTIFS('Reporte Diario'!$K:$K,Resumen!F$9,'Reporte Diario'!$L:$L,Resumen!$B29,'Reporte Diario'!$M:$M,$B$24) -> 0 | G29: =COUNTIFS('Reporte Diario'!$K:$K,Resumen!G$9,'Reporte Diario'!$L:$L,Resumen!$B29,'Reporte Diario'!$M:$M,$B$24) -> 0 | H29: =COUNTIFS('Reporte Diario'!$K:$K,Resumen!H$9,'Reporte Diario'!$L:$L,Resumen!$B29,'Reporte Diario'!$M:$M,$B$24) -> 0 | I29: =COUNTIFS('Reporte Diario'!$K:$K,Resumen!I$9,'Reporte Diario'!$L:$L,Resumen!$B29,'Reporte Diario'!$M:$M,$B$24) -> 0 | J29: =COUNTIFS('Reporte Diario'!$K:$K,Resumen!J$9,'Reporte Diario'!$L:$L,Resumen!$B29,'Reporte Diario'!$M:$M,$B$24) -> 0 | ... M29: =COUNTIFS('Reporte Diario'!$K:$K,Resumen!M$9,'Reporte Diario'!$L:$L,Resumen!$B29,'Reporte Diario'!$M:$M,$B$24) -> 0 | N29: =SUM(C29:L29) -> 0 | P29: INGENIERIA | Q29: =COUNTIFS('Reporte Diario'!$H:$H,Resumen!Q$23,'Reporte Diario'!$L:$L,$P29,'Reporte Diario'!$M:$M,$P$24,'Reporte Diario'!$K:$K,"OBRA") -> 0 | R29: =COUNTIFS('Reporte Diario'!$H:$H,Resumen!R$23,'Reporte Diario'!$L:$L,$P29,'Reporte Diario'!$M:$M,$P$24,'Reporte Diario'!$K:$K,"OBRA") -> 0 | S29: =COUNTIFS('Reporte Diario'!$H:$H,Resumen!S$23,'Reporte Diario'!$L:$L,$P29,'Reporte Diario'!$M:$M,$P$24,'Reporte Diario'!$K:$K,"OBRA") -> 0 | T29: =COUNTIFS('Reporte Diario'!$H:$H,Resumen!T$23,'Reporte Diario'!$L:$L,$P29,'Reporte Diario'!$M:$M,$P$24,'Reporte Diario'!$K:$K,"OBRA") -> 0 | U29: =COUNTIFS('Reporte Diario'!$H:$H,Resumen!U$23,'Reporte Diario'!$L:$L,$P29,'Reporte Diario'!$M:$M,$P$24,'Reporte Diario'!$K:$K,"DESCANSO") -> 0 | V29: =COUNTIFS('Reporte Diario'!$H:$H,Resumen!V$23,'Reporte Diario'!$L:$L,$P29,'Reporte Diario'!$M:$M,$P$24,'Reporte Diario'!$K:$K,"DESCANSO") -> 0 | W29: =COUNTIFS('Reporte Diario'!$H:$H,Resumen!W$23,'Reporte Diario'!$L:$L,$P29,'Reporte Diario'!$M:$M,$P$24,'Reporte Diario'!$K:$K,"DESCANSO") -> 0 | X29: =COUNTIFS('Reporte Diario'!$H:$H,Resumen!X$23,'Reporte Diario'!$L:$L,$P29,'Reporte Diario'!$M:$M,$P$24,'Reporte Diario'!$K:$K,"DESCANSO") -> 0 | Y29: =SUM(E29:M29) -> 0 | Z29: =SUM(Q29:Y29) -> 0
B30: MEDIO AMBIENTE | C30: =COUNTIFS('Reporte Diario'!$K:$K,Resumen!C$9,'Reporte Diario'!$L:$L,Resumen!$B30,'Reporte Diario'!$M:$M,$B$24) -> 0 | D30: =COUNTIFS('Reporte Diario'!$K:$K,Resumen!D$9,'Reporte Diario'!$L:$L,Resumen!$B30,'Reporte Diario'!$M:$M,$B$24) -> 0 | E30: =COUNTIFS('Reporte Diario'!$K:$K,Resumen!E$9,'Reporte Diario'!$L:$L,Resumen!$B30,'Reporte Diario'!$M:$M,$B$24) -> 0 | F30: =COUNTIFS('Reporte Diario'!$K:$K,Resumen!F$9,'Reporte Diario'!$L:$L,Resumen!$B30,'Reporte Diario'!$M:$M,$B$24) -> 0 | G30: =COUNTIFS('Reporte Diario'!$K:$K,Resumen!G$9,'Reporte Diario'!$L:$L,Resumen!$B30,'Reporte Diario'!$M:$M,$B$24) -> 0 | H30: =COUNTIFS('Reporte Diario'!$K:$K,Resumen!H$9,'Reporte Diario'!$L:$L,Resumen!$B30,'Reporte Diario'!$M:$M,$B$24) -> 0 | I30: =COUNTIFS('Reporte Diario'!$K:$K,Resumen!I$9,'Reporte Diario'!$L:$L,Resumen!$B30,'Reporte Diario'!$M:$M,$B$24) -> 0 | J30: =COUNTIFS('Reporte Diario'!$K:$K,Resumen!J$9,'Reporte Diario'!$L:$L,Resumen!$B30,'Reporte Diario'!$M:$M,$B$24) -> 0 | ... M30: =COUNTIFS('Reporte Diario'!$K:$K,Resumen!M$9,'Reporte Diario'!$L:$L,Resumen!$B30,'Reporte Diario'!$M:$M,$B$24) -> 0 | N30: =SUM(C30:L30) -> 0 | P30: MEDIO AMBIENTE | Q30: =COUNTIFS('Reporte Diario'!$H:$H,Resumen!Q$23,'Reporte Diario'!$L:$L,$P30,'Reporte Diario'!$M:$M,$P$24,'Reporte Diario'!$K:$K,"OBRA") -> 0 | R30: =COUNTIFS('Reporte Diario'!$H:$H,Resumen!R$23,'Reporte Diario'!$L:$L,$P30,'Reporte Diario'!$M:$M,$P$24,'Reporte Diario'!$K:$K,"OBRA") -> 0 | S30: =COUNTIFS('Reporte Diario'!$H:$H,Resumen!S$23,'Reporte Diario'!$L:$L,$P30,'Reporte Diario'!$M:$M,$P$24,'Reporte Diario'!$K:$K,"OBRA") -> 0 | T30: =COUNTIFS('Reporte Diario'!$H:$H,Resumen!T$23,'Reporte Diario'!$L:$L,$P30,'Reporte Diario'!$M:$M,$P$24,'Reporte Diario'!$K:$K,"OBRA") -> 0 | U30: =COUNTIFS('Reporte Diario'!$H:$H,Resumen!U$23,'Reporte Diario'!$L:$L,$P30,'Reporte Diario'!$M:$M,$P$24,'Reporte Diario'!$K:$K,"DESCANSO") -> 0 | V30: =COUNTIFS('Reporte Diario'!$H:$H,Resumen!V$23,'Reporte Diario'!$L:$L,$P30,'Reporte Diario'!$M:$M,$P$24,'Reporte Diario'!$K:$K,"DESCANSO") -> 0 | W30: =COUNTIFS('Reporte Diario'!$H:$H,Resumen!W$23,'Reporte Diario'!$L:$L,$P30,'Reporte Diario'!$M:$M,$P$24,'Reporte Diario'!$K:$K,"DESCANSO") -> 0 | X30: =COUNTIFS('Reporte Diario'!$H:$H,Resumen!X$23,'Reporte Diario'!$L:$L,$P30,'Reporte Diario'!$M:$M,$P$24,'Reporte Diario'!$K:$K,"DESCANSO") -> 0 | Y30: =SUM(E30:M30) -> 0 | Z30: =SUM(Q30:Y30) -> 0
B31: OFICINA CALIDAD | C31: =COUNTIFS('Reporte Diario'!$K:$K,Resumen!C$9,'Reporte Diario'!$L:$L,Resumen!$B31,'Reporte Diario'!$M:$M,$B$24) -> 0 | D31: =COUNTIFS('Reporte Diario'!$K:$K,Resumen!D$9,'Reporte Diario'!$L:$L,Resumen!$B31,'Reporte Diario'!$M:$M,$B$24) -> 0 | E31: =COUNTIFS('Reporte Diario'!$K:$K,Resumen!E$9,'Reporte Diario'!$L:$L,Resumen!$B31,'Reporte Diario'!$M:$M,$B$24) -> 0 | F31: =COUNTIFS('Reporte Diario'!$K:$K,Resumen!F$9,'Reporte Diario'!$L:$L,Resumen!$B31,'Reporte Diario'!$M:$M,$B$24) -> 0 | G31: =COUNTIFS('Reporte Diario'!$K:$K,Resumen!G$9,'Reporte Diario'!$L:$L,Resumen!$B31,'Reporte Diario'!$M:$M,$B$24) -> 0 | H31: =COUNTIFS('Reporte Diario'!$K:$K,Resumen!H$9,'Reporte Diario'!$L:$L,Resumen!$B31,'Reporte Diario'!$M:$M,$B$24) -> 0 | I31: =COUNTIFS('Reporte Diario'!$K:$K,Resumen!I$9,'Reporte Diario'!$L:$L,Resumen!$B31,'Reporte Diario'!$M:$M,$B$24) -> 0 | J31: =COUNTIFS('Reporte Diario'!$K:$K,Resumen!J$9,'Reporte Diario'!$L:$L,Resumen!$B31,'Reporte Diario'!$M:$M,$B$24) -> 0 | ... M31: =COUNTIFS('Reporte Diario'!$K:$K,Resumen!M$9,'Reporte Diario'!$L:$L,Resumen!$B31,'Reporte Diario'!$M:$M,$B$24) -> 0 | N31: =SUM(C31:L31) -> 0 | P31: OFICINA CALIDAD | Q31: =COUNTIFS('Reporte Diario'!$H:$H,Resumen!Q$23,'Reporte Diario'!$L:$L,$P31,'Reporte Diario'!$M:$M,$P$24,'Reporte Diario'!$K:$K,"OBRA") -> 0 | R31: =COUNTIFS('Reporte Diario'!$H:$H,Resumen!R$23,'Reporte Diario'!$L:$L,$P31,'Reporte Diario'!$M:$M,$P$24,'Reporte Diario'!$K:$K,"OBRA") -> 0 | S31: =COUNTIFS('Reporte Diario'!$H:$H,Resumen!S$23,'Reporte Diario'!$L:$L,$P31,'Reporte Diario'!$M:$M,$P$24,'Reporte Diario'!$K:$K,"OBRA") -> 0 | T31: =COUNTIFS('Reporte Diario'!$H:$H,Resumen!T$23,'Reporte Diario'!$L:$L,$P31,'Reporte Diario'!$M:$M,$P$24,'Reporte Diario'!$K:$K,"OBRA") -> 0 | U31: =COUNTIFS('Reporte Diario'!$H:$H,Resumen!U$23,'Reporte Diario'!$L:$L,$P31,'Reporte Diario'!$M:$M,$P$24,'Reporte Diario'!$K:$K,"DESCANSO") -> 0 | V31: =COUNTIFS('Reporte Diario'!$H:$H,Resumen!V$23,'Reporte Diario'!$L:$L,$P31,'Reporte Diario'!$M:$M,$P$24,'Reporte Diario'!$K:$K,"DESCANSO") -> 0 | W31: =COUNTIFS('Reporte Diario'!$H:$H,Resumen!W$23,'Reporte Diario'!$L:$L,$P31,'Reporte Diario'!$M:$M,$P$24,'Reporte Diario'!$K:$K,"DESCANSO") -> 0 | X31: =COUNTIFS('Reporte Diario'!$H:$H,Resumen!X$23,'Reporte Diario'!$L:$L,$P31,'Reporte Diario'!$M:$M,$P$24,'Reporte Diario'!$K:$K,"DESCANSO") -> 0 | Y31: =SUM(E31:M31) -> 0 | Z31: =SUM(Q31:Y31) -> 0
B32: OFICINA TECNICA | C32: =COUNTIFS('Reporte Diario'!$K:$K,Resumen!C$9,'Reporte Diario'!$L:$L,Resumen!$B32,'Reporte Diario'!$M:$M,$B$24) -> 0 | D32: =COUNTIFS('Reporte Diario'!$K:$K,Resumen!D$9,'Reporte Diario'!$L:$L,Resumen!$B32,'Reporte Diario'!$M:$M,$B$24) -> 0 | E32: =COUNTIFS('Reporte Diario'!$K:$K,Resumen!E$9,'Reporte Diario'!$L:$L,Resumen!$B32,'Reporte Diario'!$M:$M,$B$24) -> 0 | F32: =COUNTIFS('Reporte Diario'!$K:$K,Resumen!F$9,'Reporte Diario'!$L:$L,Resumen!$B32,'Reporte Diario'!$M:$M,$B$24) -> 0 | G32: =COUNTIFS('Reporte Diario'!$K:$K,Resumen!G$9,'Reporte Diario'!$L:$L,Resumen!$B32,'Reporte Diario'!$M:$M,$B$24) -> 0 | H32: =COUNTIFS('Reporte Diario'!$K:$K,Resumen!H$9,'Reporte Diario'!$L:$L,Resumen!$B32,'Reporte Diario'!$M:$M,$B$24) -> 0 | I32: =COUNTIFS('Reporte Diario'!$K:$K,Resumen!I$9,'Reporte Diario'!$L:$L,Resumen!$B32,'Reporte Diario'!$M:$M,$B$24) -> 0 | J32: =COUNTIFS('Reporte Diario'!$K:$K,Resumen!J$9,'Reporte Diario'!$L:$L,Resumen!$B32,'Reporte Diario'!$M:$M,$B$24) -> 0 | ... M32: =COUNTIFS('Reporte Diario'!$K:$K,Resumen!M$9,'Reporte Diario'!$L:$L,Resumen!$B32,'Reporte Diario'!$M:$M,$B$24) -> 0 | N32: =SUM(C32:L32) -> 0 | P32: OFICINA TECNICA | Q32: =COUNTIFS('Reporte Diario'!$H:$H,Resumen!Q$23,'Reporte Diario'!$L:$L,$P32,'Reporte Diario'!$M:$M,$P$24,'Reporte Diario'!$K:$K,"OBRA") -> 0 | R32: =COUNTIFS('Reporte Diario'!$H:$H,Resumen!R$23,'Reporte Diario'!$L:$L,$P32,'Reporte Diario'!$M:$M,$P$24,'Reporte Diario'!$K:$K,"OBRA") -> 0 | S32: =COUNTIFS('Reporte Diario'!$H:$H,Resumen!S$23,'Reporte Diario'!$L:$L,$P32,'Reporte Diario'!$M:$M,$P$24,'Reporte Diario'!$K:$K,"OBRA") -> 0 | T32: =COUNTIFS('Reporte Diario'!$H:$H,Resumen!T$23,'Reporte Diario'!$L:$L,$P32,'Reporte Diario'!$M:$M,$P$24,'Reporte Diario'!$K:$K,"OBRA") -> 0 | U32: =COUNTIFS('Reporte Diario'!$H:$H,Resumen!U$23,'Reporte Diario'!$L:$L,$P32,'Reporte Diario'!$M:$M,$P$24,'Reporte Diario'!$K:$K,"DESCANSO") -> 0 | V32: =COUNTIFS('Reporte Diario'!$H:$H,Resumen!V$23,'Reporte Diario'!$L:$L,$P32,'Reporte Diario'!$M:$M,$P$24,'Reporte Diario'!$K:$K,"DESCANSO") -> 0 | W32: =COUNTIFS('Reporte Diario'!$H:$H,Resumen!W$23,'Reporte Diario'!$L:$L,$P32,'Reporte Diario'!$M:$M,$P$24,'Reporte Diario'!$K:$K,"DESCANSO") -> 0 | X32: =COUNTIFS('Reporte Diario'!$H:$H,Resumen!X$23,'Reporte Diario'!$L:$L,$P32,'Reporte Diario'!$M:$M,$P$24,'Reporte Diario'!$K:$K,"DESCANSO") -> 0 | Y32: =SUM(E32:M32) -> 0 | Z32: =SUM(Q32:Y32) -> 0
B33: PREVENCION DE RIESGOS | C33: =COUNTIFS('Reporte Diario'!$K:$K,Resumen!C$9,'Reporte Diario'!$L:$L,Resumen!$B33,'Reporte Diario'!$M:$M,$B$24) -> 0 | D33: =COUNTIFS('Reporte Diario'!$K:$K,Resumen!D$9,'Reporte Diario'!$L:$L,Resumen!$B33,'Reporte Diario'!$M:$M,$B$24) -> 0 | E33: =COUNTIFS('Reporte Diario'!$K:$K,Resumen!E$9,'Reporte Diario'!$L:$L,Resumen!$B33,'Reporte Diario'!$M:$M,$B$24) -> 0 | F33: =COUNTIFS('Reporte Diario'!$K:$K,Resumen!F$9,'Reporte Diario'!$L:$L,Resumen!$B33,'Reporte Diario'!$M:$M,$B$24) -> 0 | G33: =COUNTIFS('Reporte Diario'!$K:$K,Resumen!G$9,'Reporte Diario'!$L:$L,Resumen!$B33,'Reporte Diario'!$M:$M,$B$24) -> 0 | H33: =COUNTIFS('Reporte Diario'!$K:$K,Resumen!H$9,'Reporte Diario'!$L:$L,Resumen!$B33,'Reporte Diario'!$M:$M,$B$24) -> 0 | I33: =COUNTIFS('Reporte Diario'!$K:$K,Resumen!I$9,'Reporte Diario'!$L:$L,Resumen!$B33,'Reporte Diario'!$M:$M,$B$24) -> 0 | J33: =COUNTIFS('Reporte Diario'!$K:$K,Resumen!J$9,'Reporte Diario'!$L:$L,Resumen!$B33,'Reporte Diario'!$M:$M,$B$24) -> 0 | ... M33: =COUNTIFS('Reporte Diario'!$K:$K,Resumen!M$9,'Reporte Diario'!$L:$L,Resumen!$B33,'Reporte Diario'!$M:$M,$B$24) -> 0 | N33: =SUM(C33:L33) -> 0 | P33: PREVENCION DE RIESGOS | Q33: =COUNTIFS('Reporte Diario'!$H:$H,Resumen!Q$23,'Reporte Diario'!$L:$L,$P33,'Reporte Diario'!$M:$M,$P$24,'Reporte Diario'!$K:$K,"OBRA") -> 0 | R33: =COUNTIFS('Reporte Diario'!$H:$H,Resumen!R$23,'Reporte Diario'!$L:$L,$P33,'Reporte Diario'!$M:$M,$P$24,'Reporte Diario'!$K:$K,"OBRA") -> 0 | S33: =COUNTIFS('Reporte Diario'!$H:$H,Resumen!S$23,'Reporte Diario'!$L:$L,$P33,'Reporte Diario'!$M:$M,$P$24,'Reporte Diario'!$K:$K,"OBRA") -> 0 | T33: =COUNTIFS('Reporte Diario'!$H:$H,Resumen!T$23,'Reporte Diario'!$L:$L,$P33,'Reporte Diario'!$M:$M,$P$24,'Reporte Diario'!$K:$K,"OBRA") -> 0 | U33: =COUNTIFS('Reporte Diario'!$H:$H,Resumen!U$23,'Reporte Diario'!$L:$L,$P33,'Reporte Diario'!$M:$M,$P$24,'Reporte Diario'!$K:$K,"DESCANSO") -> 0 | V33: =COUNTIFS('Reporte Diario'!$H:$H,Resumen!V$23,'Reporte Diario'!$L:$L,$P33,'Reporte Diario'!$M:$M,$P$24,'Reporte Diario'!$K:$K,"DESCANSO") -> 0 | W33: =COUNTIFS('Reporte Diario'!$H:$H,Resumen!W$23,'Reporte Diario'!$L:$L,$P33,'Reporte Diario'!$M:$M,$P$24,'Reporte Diario'!$K:$K,"DESCANSO") -> 0 | X33: =COUNTIFS('Reporte Diario'!$H:$H,Resumen!X$23,'Reporte Diario'!$L:$L,$P33,'Reporte Diario'!$M:$M,$P$24,'Reporte Diario'!$K:$K,"DESCANSO") -> 0 | Y33: =SUM(E33:M33) -> 0 | Z33: =SUM(Q33:Y33) -> 0
B34: STAFF SUPERIOR | C34: =COUNTIFS('Reporte Diario'!$K:$K,Resumen!C$9,'Reporte Diario'!$L:$L,Resumen!$B34,'Reporte Diario'!$M:$M,$B$24) -> 0 | D34: =COUNTIFS('Reporte Diario'!$K:$K,Resumen!D$9,'Reporte Diario'!$L:$L,Resumen!$B34,'Reporte Diario'!$M:$M,$B$24) -> 0 | E34: =COUNTIFS('Reporte Diario'!$K:$K,Resumen!E$9,'Reporte Diario'!$L:$L,Resumen!$B34,'Reporte Diario'!$M:$M,$B$24) -> 0 | F34: =COUNTIFS('Reporte Diario'!$K:$K,Resumen!F$9,'Reporte Diario'!$L:$L,Resumen!$B34,'Reporte Diario'!$M:$M,$B$24) -> 0 | G34: =COUNTIFS('Reporte Diario'!$K:$K,Resumen!G$9,'Reporte Diario'!$L:$L,Resumen!$B34,'Reporte Diario'!$M:$M,$B$24) -> 0 | H34: =COUNTIFS('Reporte Diario'!$K:$K,Resumen!H$9,'Reporte Diario'!$L:$L,Resumen!$B34,'Reporte Diario'!$M:$M,$B$24) -> 0 | I34: =COUNTIFS('Reporte Diario'!$K:$K,Resumen!I$9,'Reporte Diario'!$L:$L,Resumen!$B34,'Reporte Diario'!$M:$M,$B$24) -> 0 | J34: =COUNTIFS('Reporte Diario'!$K:$K,Resumen!J$9,'Reporte Diario'!$L:$L,Resumen!$B34,'Reporte Diario'!$M:$M,$B$24) -> 0 | ... M34: =COUNTIFS('Reporte Diario'!$K:$K,Resumen!M$9,'Reporte Diario'!$L:$L,Resumen!$B34,'Reporte Diario'!$M:$M,$B$24) -> 0 | N34: =SUM(C34:L34) -> 0 | P34: STAFF SUPERIOR | Q34: =COUNTIFS('Reporte Diario'!$H:$H,Resumen!Q$23,'Reporte Diario'!$L:$L,$P34,'Reporte Diario'!$M:$M,$P$24,'Reporte Diario'!$K:$K,"OBRA") -> 0 | R34: =COUNTIFS('Reporte Diario'!$H:$H,Resumen!R$23,'Reporte Diario'!$L:$L,$P34,'Reporte Diario'!$M:$M,$P$24,'Reporte Diario'!$K:$K,"OBRA") -> 0 | S34: =COUNTIFS('Reporte Diario'!$H:$H,Resumen!S$23,'Reporte Diario'!$L:$L,$P34,'Reporte Diario'!$M:$M,$P$24,'Reporte Diario'!$K:$K,"OBRA") -> 0 | T34: =COUNTIFS('Reporte Diario'!$H:$H,Resumen!T$23,'Reporte Diario'!$L:$L,$P34,'Reporte Diario'!$M:$M,$P$24,'Reporte Diario'!$K:$K,"OBRA") -> 0 | U34: =COUNTIFS('Reporte Diario'!$H:$H,Resumen!U$23,'Reporte Diario'!$L:$L,$P34,'Reporte Diario'!$M:$M,$P$24,'Reporte Diario'!$K:$K,"DESCANSO") -> 0 | V34: =COUNTIFS('Reporte Diario'!$H:$H,Resumen!V$23,'Reporte Diario'!$L:$L,$P34,'Reporte Diario'!$M:$M,$P$24,'Reporte Diario'!$K:$K,"DESCANSO") -> 0 | W34: =COUNTIFS('Reporte Diario'!$H:$H,Resumen!W$23,'Reporte Diario'!$L:$L,$P34,'Reporte Diario'!$M:$M,$P$24,'Reporte Diario'!$K:$K,"DESCANSO") -> 0 | X34: =COUNTIFS('Reporte Diario'!$H:$H,Resumen!X$23,'Reporte Diario'!$L:$L,$P34,'Reporte Diario'!$M:$M,$P$24,'Reporte Diario'!$K:$K,"DESCANSO") -> 0 | Y34: =SUM(E34:M34) -> 0 | Z34: =SUM(Q34:Y34) -> 0
B35: SECRETARIO TECNICO | C35: =COUNTIFS('Reporte Diario'!$K:$K,Resumen!C$9,'Reporte Diario'!$L:$L,Resumen!$B35,'Reporte Diario'!$M:$M,$B$24) -> 0 | D35: =COUNTIFS('Reporte Diario'!$K:$K,Resumen!D$9,'Reporte Diario'!$L:$L,Resumen!$B35,'Reporte Diario'!$M:$M,$B$24) -> 0 | E35: =COUNTIFS('Reporte Diario'!$K:$K,Resumen!E$9,'Reporte Diario'!$L:$L,Resumen!$B35,'Reporte Diario'!$M:$M,$B$24) -> 0 | F35: =COUNTIFS('Reporte Diario'!$K:$K,Resumen!F$9,'Reporte Diario'!$L:$L,Resumen!$B35,'Reporte Diario'!$M:$M,$B$24) -> 0 | G35: =COUNTIFS('Reporte Diario'!$K:$K,Resumen!G$9,'Reporte Diario'!$L:$L,Resumen!$B35,'Reporte Diario'!$M:$M,$B$24) -> 0 | H35: =COUNTIFS('Reporte Diario'!$K:$K,Resumen!H$9,'Reporte Diario'!$L:$L,Resumen!$B35,'Reporte Diario'!$M:$M,$B$24) -> 0 | I35: =COUNTIFS('Reporte Diario'!$K:$K,Resumen!I$9,'Reporte Diario'!$L:$L,Resumen!$B35,'Reporte Diario'!$M:$M,$B$24) -> 0 | J35: =COUNTIFS('Reporte Diario'!$K:$K,Resumen!J$9,'Reporte Diario'!$L:$L,Resumen!$B35,'Reporte Diario'!$M:$M,$B$24) -> 0 | ... M35: =COUNTIFS('Reporte Diario'!$K:$K,Resumen!M$9,'Reporte Diario'!$L:$L,Resumen!$B35,'Reporte Diario'!$M:$M,$B$24) -> 0 | N35: =SUM(C35:L35) -> 0 | P35: SECRETARIO TECNICO | Q35: =COUNTIFS('Reporte Diario'!$H:$H,Resumen!Q$23,'Reporte Diario'!$L:$L,$P35,'Reporte Diario'!$M:$M,$P$24,'Reporte Diario'!$K:$K,"OBRA") -> 0 | R35: =COUNTIFS('Reporte Diario'!$H:$H,Resumen!R$23,'Reporte Diario'!$L:$L,$P35,'Reporte Diario'!$M:$M,$P$24,'Reporte Diario'!$K:$K,"OBRA") -> 0 | S35: =COUNTIFS('Reporte Diario'!$H:$H,Resumen!S$23,'Reporte Diario'!$L:$L,$P35,'Reporte Diario'!$M:$M,$P$24,'Reporte Diario'!$K:$K,"OBRA") -> 0 | T35: =COUNTIFS('Reporte Diario'!$H:$H,Resumen!T$23,'Reporte Diario'!$L:$L,$P35,'Reporte Diario'!$M:$M,$P$24,'Reporte Diario'!$K:$K,"OBRA") -> 0 | U35: =COUNTIFS('Reporte Diario'!$H:$H,Resumen!U$23,'Reporte Diario'!$L:$L,$P35,'Reporte Diario'!$M:$M,$P$24,'Reporte Diario'!$K:$K,"DESCANSO") -> 0 | V35: =COUNTIFS('Reporte Diario'!$H:$H,Resumen!V$23,'Reporte Diario'!$L:$L,$P35,'Reporte Diario'!$M:$M,$P$24,'Reporte Diario'!$K:$K,"DESCANSO") -> 0 | W35: =COUNTIFS('Reporte Diario'!$H:$H,Resumen!W$23,'Reporte Diario'!$L:$L,$P35,'Reporte Diario'!$M:$M,$P$24,'Reporte Diario'!$K:$K,"DESCANSO") -> 0 | X35: =COUNTIFS('Reporte Diario'!$H:$H,Resumen!X$23,'Reporte Diario'!$L:$L,$P35,'Reporte Diario'!$M:$M,$P$24,'Reporte Diario'!$K:$K,"DESCANSO") -> 0 | Y35: =SUM(E35:M35) -> 0 | Z35: =SUM(Q35:Y35) -> 0
B36: SERVICIOS | C36: =COUNTIFS('Reporte Diario'!$K:$K,Resumen!C$9,'Reporte Diario'!$L:$L,Resumen!$B36,'Reporte Diario'!$M:$M,$B$24) -> 0 | D36: =COUNTIFS('Reporte Diario'!$K:$K,Resumen!D$9,'Reporte Diario'!$L:$L,Resumen!$B36,'Reporte Diario'!$M:$M,$B$24) -> 0 | E36: =COUNTIFS('Reporte Diario'!$K:$K,Resumen!E$9,'Reporte Diario'!$L:$L,Resumen!$B36,'Reporte Diario'!$M:$M,$B$24) -> 0 | F36: =COUNTIFS('Reporte Diario'!$K:$K,Resumen!F$9,'Reporte Diario'!$L:$L,Resumen!$B36,'Reporte Diario'!$M:$M,$B$24) -> 0 | G36: =COUNTIFS('Reporte Diario'!$K:$K,Resumen!G$9,'Reporte Diario'!$L:$L,Resumen!$B36,'Reporte Diario'!$M:$M,$B$24) -> 0 | H36: =COUNTIFS('Reporte Diario'!$K:$K,Resumen!H$9,'Reporte Diario'!$L:$L,Resumen!$B36,'Reporte Diario'!$M:$M,$B$24) -> 0 | I36: =COUNTIFS('Reporte Diario'!$K:$K,Resumen!I$9,'Reporte Diario'!$L:$L,Resumen!$B36,'Reporte Diario'!$M:$M,$B$24) -> 0 | J36: =COUNTIFS('Reporte Diario'!$K:$K,Resumen!J$9,'Reporte Diario'!$L:$L,Resumen!$B36,'Reporte Diario'!$M:$M,$B$24) -> 0 | ... M36: =COUNTIFS('Reporte Diario'!$K:$K,Resumen!M$9,'Reporte Diario'!$L:$L,Resumen!$B36,'Reporte Diario'!$M:$M,$B$24) -> 0 | N36: =SUM(C36:L36) -> 0 | P36: SERVICIOS | Q36: =COUNTIFS('Reporte Diario'!$H:$H,Resumen!Q$23,'Reporte Diario'!$L:$L,$P36,'Reporte Diario'!$M:$M,$P$24,'Reporte Diario'!$K:$K,"OBRA") -> 0 | R36: =COUNTIFS('Reporte Diario'!$H:$H,Resumen!R$23,'Reporte Diario'!$L:$L,$P36,'Reporte Diario'!$M:$M,$P$24,'Reporte Diario'!$K:$K,"OBRA") -> 0 | S36: =COUNTIFS('Reporte Diario'!$H:$H,Resumen!S$23,'Reporte Diario'!$L:$L,$P36,'Reporte Diario'!$M:$M,$P$24,'Reporte Diario'!$K:$K,"OBRA") -> 0 | T36: =COUNTIFS('Reporte Diario'!$H:$H,Resumen!T$23,'Reporte Diario'!$L:$L,$P36,'Reporte Diario'!$M:$M,$P$24,'Reporte Diario'!$K:$K,"OBRA") -> 0 | U36: =COUNTIFS('Reporte Diario'!$H:$H,Resumen!U$23,'Reporte Diario'!$L:$L,$P36,'Reporte Diario'!$M:$M,$P$24,'Reporte Diario'!$K:$K,"DESCANSO") -> 0 | V36: =COUNTIFS('Reporte Diario'!$H:$H,Resumen!V$23,'Reporte Diario'!$L:$L,$P36,'Reporte Diario'!$M:$M,$P$24,'Reporte Diario'!$K:$K,"DESCANSO") -> 0 | W36: =COUNTIFS('Reporte Diario'!$H:$H,Resumen!W$23,'Reporte Diario'!$L:$L,$P36,'Reporte Diario'!$M:$M,$P$24,'Reporte Diario'!$K:$K,"DESCANSO") -> 0 | X36: =COUNTIFS('Reporte Diario'!$H:$H,Resumen!X$23,'Reporte Diario'!$L:$L,$P36,'Reporte Diario'!$M:$M,$P$24,'Reporte Diario'!$K:$K,"DESCANSO") -> 0 | Y36: =SUM(E36:M36) -> 0 | Z36: =SUM(Q36:Y36) -> 0
... B39: TOPOGRAFIA | C39: =COUNTIFS('Reporte Diario'!$K:$K,Resumen!C$9,'Reporte Diario'!$L:$L,Resumen!$B39,'Reporte Diario'!$M:$M,$B$24) -> 0 | D39: =COUNTIFS('Reporte Diario'!$K:$K,Resumen!D$9,'Reporte Diario'!$L:$L,Resumen!$B39,'Reporte Diario'!$M:$M,$B$24) -> 0 | E39: =COUNTIFS('Reporte Diario'!$K:$K,Resumen!E$9,'Reporte Diario'!$L:$L,Resumen!$B39,'Reporte Diario'!$M:$M,$B$24) -> 0 | F39: =COUNTIFS('Reporte Diario'!$K:$K,Resumen!F$9,'Reporte Diario'!$L:$L,Resumen!$B39,'Reporte Diario'!$M:$M,$B$24) -> 0 | G39: =COUNTIFS('Reporte Diario'!$K:$K,Resumen!G$9,'Reporte Diario'!$L:$L,Resumen!$B39,'Reporte Diario'!$M:$M,$B$24) -> 0 | H39: =COUNTIFS('Reporte Diario'!$K:$K,Resumen!H$9,'Reporte Diario'!$L:$L,Resumen!$B39,'Reporte Diario'!$M:$M,$B$24) -> 0 | I39: =COUNTIFS('Reporte Diario'!$K:$K,Resumen!I$9,'Reporte Diario'!$L:$L,Resumen!$B39,'Reporte Diario'!$M:$M,$B$24) -> 0 | J39: =COUNTIFS('Reporte Diario'!$K:$K,Resumen!J$9,'Reporte Diario'!$L:$L,Resumen!$B39,'Reporte Diario'!$M:$M,$B$24) -> 0 | ... M39: =COUNTIFS('Reporte Diario'!$K:$K,Resumen!M$9,'Reporte Diario'!$L:$L,Resumen!$B39,'Reporte Diario'!$M:$M,$B$24) -> 0 | N39: =SUM(C39:L39) -> 0 | P39: TOPOGRAFIA | Q39: =COUNTIFS('Reporte Diario'!$H:$H,Resumen!Q$23,'Reporte Diario'!$L:$L,$P39,'Reporte Diario'!$M:$M,$P$24,'Reporte Diario'!$K:$K,"OBRA") -> 0 | R39: =COUNTIFS('Reporte Diario'!$H:$H,Resumen!R$23,'Reporte Diario'!$L:$L,$P39,'Reporte Diario'!$M:$M,$P$24,'Reporte Diario'!$K:$K,"OBRA") -> 0 | S39: =COUNTIFS('Reporte Diario'!$H:$H,Resumen!S$23,'Reporte Diario'!$L:$L,$P39,'Reporte Diario'!$M:$M,$P$24,'Reporte Diario'!$K:$K,"OBRA") -> 0 | T39: =COUNTIFS('Reporte Diario'!$H:$H,Resumen!T$23,'Reporte Diario'!$L:$L,$P39,'Reporte Diario'!$M:$M,$P$24,'Reporte Diario'!$K:$K,"OBRA") -> 0 | U39: =COUNTIFS('Reporte Diario'!$H:$H,Resumen!U$23,'Reporte Diario'!$L:$L,$P39,'Reporte Diario'!$M:$M,$P$24,'Reporte Diario'!$K:$K,"DESCANSO") -> 0 | V39: =COUNTIFS('Reporte Diario'!$H:$H,Resumen!V$23,'Reporte Diario'!$L:$L,$P39,'Reporte Diario'!$M:$M,$P$24,'Reporte Diario'!$K:$K,"DESCANSO") -> 0 | W39: =COUNTIFS('Reporte Diario'!$H:$H,Resumen!W$23,'Reporte Diario'!$L:$L,$P39,'Reporte Diario'!$M:$M,$P$24,'Reporte Diario'!$K:$K,"DESCANSO") -> 0 | X39: =COUNTIFS('Reporte Diario'!$H:$H,Resumen!X$23,'Reporte Diario'!$L:$L,$P39,'Reporte Diario'!$M:$M,$P$24,'Reporte Diario'!$K:$K,"DESCANSO") -> 0 | Y39: =SUM(E39:M39) -> 0 | Z39: =SUM(Q39:Y39) -> 0
B41: TOTAL CONTRATADOS | C41: =C10+C24 -> 0 | D41: =D10+D24 -> 0 | E41: =E10+E24 -> 0 | F41: =F10+F24 -> 0 | G41: =G10+G24 -> 0 | H41: =H10+H24 -> 0 | I41: =I10+I24 -> 0 | J41: =J10+J24 -> 0 | ... M41: =M10+M24 -> 0 | N41: =SUM(C41:L41) -> 0 | P41: TOTAL CONTRATADOS | Q41: =Q10+Q24 -> 0 | R41: =R10+R24 -> 0 | S41: =S10+S24 -> 0 | T41: =T10+T24 -> 0 | U41: =U10+U24 -> 0 | V41: =V10+V24 -> 0 | W41: =W10+W24 -> 0 | X41: =X10+X24 -> 0 | Y41: =Y10+Y24 -> 0 | Z41: =SUM(Q41:Y41) -> 0

Sheet Hoja1
A1: CARGO | B1: UNIDAD | C1: MOD
A2: CAPATAZ AISLACION | B2: AISLACION | C2: MOD
A3: M.1ª AISLACION | B3: AISLACION | C3: MOD
A4: M.2ª AISLACION | B4: AISLACION | C4: MOD
A5: M.M. AISLACION | B5: AISLACION | C5: MOD
A6: MAESTRO 1ERA. AISLACION/ANDAMIO | B6: AISLACION | C6: MOD
A7: AYUDANTE ANDAMIOS | B7: ANDAMIOS | C7: MOD
A8: CAPATAZ ANDAMIOS | B8: ANDAMIOS | C8: MOD
A9: CAPATAZ ANDAMIOS/AISLACION | B9: ANDAMIOS | C9: MOD
A10: M.2ª ANDAMIOS | B10: ANDAMIOS | C10: MOD
A11: M.M. ANDAMIOS | B11: ANDAMIOS | C11: MOD
A12: Maestro de 1ra Andamios | B12: ANDAMIOS | C12: MOD
... A1132: Gerente Relaciones Laborales | B1132: STAFF | C1132: MOI

Sheet Mantenedor
A1: 05X02 | B1: DESCANSO | C1: ANDAMIOS | D1: L-V | E1: I: de Tarapacá | F1: Algarrobo
A2: 14X14 | B2: OBRA | C2: AISLACIÓN | D2: A | E2: II: de Antofagasta | F2: Alto Biobío
A3: 10X05 | B3: OFICINA OBRA | C3: CAÑERIA | D3: B | E3: III: de Atacama | F3: Alto Hospicio
A4: 11X03 | B4: OFICINA CCP | C4: INSTRUMENTACION | D4: C | E4: IV: de Coquimbo | F4: Ancud
A5: 08X06 | B5: BODEGA SAN BERNANDO | C5: ELECTRICOS | D5: D | E5: IX: de la Araucanía | F5: Angol
A6: 14X07 | B6: OFICINA CENTRAL | C6: ENFIERRADURA | D6: E | E6: RM: Metropolitana de Santiago | F6: Antofagasta
A7: 04X03 | B7: FALLA | C7: ESTRUCTURA | D7: F | E7: V: de Valparaíso | F7: Antuco
A8: 04X04 | B8: LICENCIA MATERNAL | C8: MECANICA | D8: G | E8: VI: del Libertador Gral. Bernardo O'Higgins | F8: Arauco
A9: 07X07 | B9: LICENCIA MEDICA | C9: PINTURA | D9: H | E9: VII: del Maule | F9: Arica
A10: 10X10 | B10: LICENCIA MUTUAL | C10: OBRAS CIVILES | E10: VIII: del Biobío | F10: Buin
A11: 10X04 | B11: OFICINA DE OBRA | C11: SOLDADURA | E11: X: de Los Lagos | F11: Bulnes
A12: 11X09 | B12: PERMISO C/S | C12: ADMINISTRACION | E12: XII: de Magallanes y de la Antártica Chilena | F12: Cabildo
A13: 20X10 | B13: PERMISO S/S | C13: BODEGA | E13: XIV: de Los Ríos | F13: Cabrero
A14: 15X07 | B14: TELETRABAJO | C14: ELECTRICOS MANTENCION | E14: XV: de Arica y Parinacota | F14: Calama
A15: 09X05 BISEMANAL | B15: EN TRANSITO | C15: EQUIPOS | E15: XVI: de Ñuble | F15: Caldera
A16: 09X05 ESPECIAL | B16: FINIQUITADO | C16: INGENIERIA | F16: Calera de Tango
A17: 15X13 | B17: VACACIONES | C17: MEDIO AMBIENTE | F17: Calle Larga
A18: 10X5 MAPA | B18: ACREDITACIÓN | C18: OFICINA CALIDAD | F18: Canela
A19: 8X6 RAJO INCA | B19: EN PROCESO | C19: OFICINA TECNICA | F19: Cañete
A20: 06X01 | C20: PREVENCION DE RIESGOS | F20: Castro
A21: 21X07 | C21: STAFF SUPERIOR | F21: Catemu
C22: SECRETARIO TECNICO | F22: Cauquenes
C23: SERVICIOS | F23: Cerrillos
C24: SUPERVISIÓN | F24: Cerro Navia
C25: TERRENO | F25: Chépica
C26: TOPOGRAFIA | F26: Chiguayante
F27: Chillán
F28: Chillán Viejo
F29: Chimbarongo
F30: Cholchol
F31: Codegua
F32: Coelemu
F33: Coihueco
F34: Coinco
F35: Colbún
F36: Colina
F37: Collipulli
F38: Coltauco
... F243: Yungay

Sheet Datos Proyecto
A1: Proyecto | B1: Fecha Asistencia | C1: Correo | D1: Versión
A2: =+'Reporte Diario'!E3 -> EIMI00359 | B2: =+'Reporte Diario'!E4 -> 46152 | C2: =+'Reporte Diario'!E5 -> atapiab@eimontajes.cl | D2: =+'Reporte Diario'!E6 -> 0

Sheet Data Obra Perú
A1: Centro de costos | B1: Nombre contrato | C1: Sobrenombre | D1: Cliente | E1: Ubicación | F1: Región | G1: Estado
A2: MIPE00101 | B2: SERVICIOS ELECTROMECANICA SISTEMA DE MANEJO - PROYECTO IPCC | C2: Correas Trasportadoras 6KM | D2: SOCIEDAD MINERA CERRO VERDE S.A.A. | E2: AREQUIPA | F2: Cusco-Apurímac | G2: Activo
A3: MIPE00102 | B3: TALLERES DE MANTENIMIENTO CONCENTRADORA CUAJONE | C3: CONCENTRADORA CUAJONE | D3: SOUTHERN PERU COPPER CORPORATION | E3: TORATA | F3: MOQUEGUA | G3: Activo
A4: MIPE00103 | B4: REUBICACION SALA ELECTRICA FAJA 10 COLECCIÓN POLVOS CUAJONE | C4: COLECCIÓN POLVOS CUAJONE | D4: SOUTHERN PERU COPPER CORPORATION | E4: TORARA | F4: MOQUEGUA | G4: Activo
A5: MIPE00010 | B5: OFICINA CENTRAL PERÚ | C5: OFICINA CENTRAL PERÚ | D5: OFICINA CENTRAL PERÚ | E5: LIMA | G5: Terminado Revisión

Sheet Data obras
A1: Id | B1: Centro de costos | C1: Nombre contrato | D1: Sobrenombre | E1: Ubicación | F1: Cliente | G1: Estado | H1: Región
A2: 180 | B2: EIMI00003 | C2: SAN BERNARDO | D2: SAN BERNARDO | E2: SAN BERNARDO | F2: SAN BERNARDO | G2: Terminado Revisión
A3: 179 | B3: EIMI00011 | C3: OFICINA CENTRAL EIMI 2.0 | D3: OFICINA CENTRAL | E3: SANTIAGO | F3: OFICINA CENTRAL | G3: Terminado Revisión
A4: 178 | B4: EIMI00012-100 | C4: OFICINAS REGIONALES - SUCURSAL CONCEPCION | D4: SUCURSAL CONCEPCION | E4: CONCEPCIÓN | F4: SUCURSAL CONCEPCION | G4: Terminado Revisión
A5: 4 | B5: EIMI00357 | C5: QB2 Chancador Primario y otros | D5: QB2 | E5: Iquique | F5: BECHTEL | G5: Terminado Revisión
A6: 5 | B6: EIMI00359 | C6: OO.CC y Montaje Electromecánico MAPA Calderas | D6: MAPA | E6: Concepción - Arauco | F6: Arauco | G6: Terminado Revisión
A7: 16 | B7: EIMI00379 | C7: SERVICIOS MULTIDISCIPLINARIOS | D7: TENIENTE - SERVICIOS MULTIDISCIPLINARIOS | E7: Rancagua | F7: CODELCO | G7: Activo
A8: 22 | B8: EIMI00384 | C8: ELECTROMECANICO PROYECTO UPGRADE EVAPORADORES SF2 PLANTA SAN | D8: CMPC - MONTAJE EVAPORADORES | E8: Nacimiento | F8: CMPC PULP SPA | G8: Activo
A9: 143 | B9: EIMI00387 | C9: EPC Muelle Centinela | D9: EPC Muelle Centinela | E9: Sierra Gorda | F9: MINERA CENTINELA | G9: Activo
A10: 144 | B10: EIMI00388 | C10: Montaje Civil Electromecánico Proyecto Estanque de Contacto Planta Nueva Aldea | D10: Montaje Electromecánico Proyecto CM, Nueva Aldea | E10: Arauco | F10: CELULOSA ARAUCO Y CONSTITUCION S.A. | G10: Activo
A11: 146 | B11: EIMI00389 | C11: K484 ENAP - SWS and WSA unit - Aconcagua Refinery, Chile - I03 General Construction Works | D11: ERA Planta de Azufre | E11: Concón | F11: Ingeniería y Construcción Tecnimont Chile y Cia Ltda | G11: Activo
A12: 150 | B12: EIMI00393 | C12: Obras de mejoramiento taller la junta N° Contrato 4600027978 | D12: La Junta Teniente | E12: Rancagua | F12: Codelco | G12: Activo
A13: 152 | B13: EIMI00395 | C13: “Construcción y Montaje Civil Electromecánico Nuevo Concentrador 1D, Planta Valdivia" | D13: Arauco Valdivia Concentrador | E13: Valdivia | F13: Celulosa Arauco | G13: Activo
... A30: 181 | B30: EIMI00414 | C30: Servicios de Obras Multidisciplinarias MGA N° Contrato 4600027683 | D30: MGA3 | E30: Rancagua | F30: CODELCO | G30: Activo
B31: MIPE00101 | C31: SERVICIOS ELECTROMECANICA SISTEMA DE MANEJO - PROYECTO IPCC | D31: Correas Trasportadoras 6KM | E31: AREQUIPA | F31: SOCIEDAD MINERA CERRO VERDE S.A.A. | G31: Activo
B32: MIPE00102 | C32: TALLERES DE MANTENIMIENTO CONCENTRADORA CUAJONE | D32: CONCENTRADORA CUAJONE | E32: TORATA | F32: SOUTHERN PERU COPPER CORPORATION | G32: Activo
B33: MIPE00103 | C33: REUBICACION SALA ELECTRICA FAJA 10 COLECCIÓN POLVOS CUAJONE | D33: COLECCIÓN POLVOS CUAJONE | E33: TORARA | F33: SOUTHERN PERU COPPER CORPORATION | G33: Activo
B34: MIPE00010 | C34: OFICINA CENTRAL PERÚ | D34: OFICINA CENTRAL PERÚ | E34: LIMA | F34: OFICINA CENTRAL PERÚ | G34: Terminado Revisión
B35: MIPE00101 | C35: SERVICIOS ELECTROMECANICA SISTEMA DE MANEJO - PROYECTO IPCC | D35: Correas Trasportadoras 6KM | E35: AREQUIPA | F35: SOCIEDAD MINERA CERRO VERDE S.A.A. | G35: Activo | H35: Cusco-Apurímac
B36: MIPE00102 | C36: TALLERES DE MANTENIMIENTO CONCENTRADORA CUAJONE | D36: CONCENTRADORA CUAJONE | E36: TORATA | F36: SOUTHERN PERU COPPER CORPORATION | G36: Activo | H36: MOQUEGUA
B37: MIPE00103 | C37: REUBICACION SALA ELECTRICA FAJA 10 COLECCIÓN POLVOS CUAJONE | D37: COLECCIÓN POLVOS CUAJONE | E37: TORARA | F37: SOUTHERN PERU COPPER CORPORATION | G37: Activo | H37: MOQUEGUA
B38: MIPE00010 | C38: OFICINA CENTRAL PERÚ | D38: OFICINA CENTRAL PERÚ | E38: LIMA | F38: OFICINA CENTRAL PERÚ | G38: Terminado Revisión
